Workbook

Sheet Instructions
A1: TIBMM Assessment Tool
A2: Threat Intelligence Behavior Maturity Model — Self-Assessment
B4: About This Assessment
B5: This workbook assesses the maturity of a Cyber Threat Intelligence (CTI) function using the Threat Intelligence Behavior Maturity Model (TIBMM). TIBMM is tuned for a Canadian telco CTI team operating alongside a SOC, and is a sibling to the Detection Engineering Behavior Maturity Model (DEBMM).
B7: It covers 26 criteria across 5 progressive tiers (T0–T4) plus 2 enrichment dimensions (Tradecraft, Governance), with 35 dropdown questions total.
B8: All questions use dropdowns (Yes/No or Scale 1—5). No free-text required.
B10: How to Use
B11: 1. Go to the Assessment tab and fill in your organization details
B12: 2. Answer each question using the dropdown menus in the amber column
B13: 3. For Yes/No questions — select from the dropdown
B14: 4. For Scale questions (1—5) — select your maturity rating
B15: 5. If any term in a question is unfamiliar (PIR, ICD 203, CMF, TaHiTI, Admiralty Code, etc.), open the Glossary tab for a short definition
B16: 6. Switch to the Results Dashboard tab to see scores calculated automatically
B18: Understanding the Model
B19: TIBMM Core Tiers | C19: Enrichment Dimensions
B20: Tier 0 — Foundation | C20: Tradecraft & Analyst Capability
B21: Role, IOC handling, source list, stakeholder touchpoints | C21: ICD 203 adherence, framework literacy, peer review
B22: Tier 1 — Basic | C22: Governance, Legal & Improvement
B23: PIRs, product template (BLUF), calibrated language, CMF | C23: PIPEDA / CRTC / Bill C-26 review, CCTX sharing, self-assessment
B24: Tier 2 — Operational
B25: TIP + IOC pipeline, DE handoff, Hunt-team partnership, IR enrichment | C25: These enrichment dimensions capture
B26: Tier 3 — Advanced | C26: tradecraft and governance factors.
B27: Vuln intel, telco fraud, TPRM, Cyber Threat Landscape reporting | C27: They contribute to the overall score
B28: Tier 4 — Leading | C28: but do not affect TIBMM tier determination.
B29: Strategic intel, SATs, outcome attribution, forecast calibration
B31: Maturity Levels
B32: Each criterion is scored on a 1—5 scale:
B34: 1 — Initial Minimal or no structured activity
B35: 2 — Repeatable Sporadic, inconsistent efforts
B36: 3 — Defined Regular, documented processes followed consistently
B37: 4 — Managed Comprehensive, well-integrated with measurable outcomes
B38: 5 — Optimized Fully automated, continuously improving
B40: Tier Determination
B41: Your achieved TIBMM tier is the highest tier where ALL criteria in that tier (and all lower tiers) score ≥ 3.0 (Defined level). This enforces the progressive nature of the model — solid foundations must precede claiming advanced maturity.
B43: Enrichment dimensions (Tradecraft, Governance) contribute to the overall maturity score but are not part of the tier determination logic. A weak enrichment score with a strong tier score predicts fragility under scrutiny.
B45: Canadian Telco Context
... B61: MITRE ATT&CK: https://attack.mitre.org/

Sheet Assessment
A1: TIBMM Assessment
A2: Threat Intelligence Behavior Maturity Model
C4: Organization:
C5: Assessor Name:
C6: Assessor Role:
C7: Date:
C8: Assessment Type: | D8: Self-Assessment
B10: TIBMM CORE ASSESSMENT — Tiers 0—4
B11: Rate your team across the 5 progressive TIBMM tiers. Your achieved tier is the highest where all criteria score ≥ 3.0.
B12: ID | C12: Criterion | D12: Question | E12: Answer | F12: Score
B13: TIER 0: FOUNDATION
B14: The CTI function exists as a distinct capability with a known scope.
B15: T0-Q1 | C15: Mission, Charter, and Service Catalog | D15: Rate the maturity of your CTI team's charter, mission, and service catalog. 1 — No written charter or service catalog; stakeholder descriptions of CTI's role diverge significantly 2 — Informal 1-page description exists; not signed off, not socialized (<30% of stakeholders have seen it) 3 — Current charter approved in the last 12 months; service catalog lists at least 3 service types; stakeholders can describe what CTI delivers 4 — Annual review on calendar; RACI defined with stakeholders; intake queue lives in a ticketing system 5 — Service-level usage metrics reported quarterly; charter referenced in budget and headcount conversations | F15: =IF(E15="","",E15)
B16: T0-Q2 | C16: Mission, Charter, and Service Catalog | D16: Does your CTI team have a published service catalog naming the products and services it delivers? | F16: =IF(E16="Yes",3,IF(E16="No",1,""))
B17: T0-Q3 | C17: Indicator of Compromise Handling | D17: Rate the maturity of your team's Indicator of Compromise (IOC) handling. 1 — No queue; IOCs handled ad-hoc by whoever notices; no record of IOCs actioned in the last 90 days 2 — Manual forwarding to SOC or hunt on best-effort basis; <50% enriched before handoff 3 — Documented triage SOP; >=80% of IOCs carry source, confidence, and disposition; named downstream owners 4 — TIP or ticket-based tracking; >=90% capture disposition; true/false-positive feedback rate measured 5 — >=80% of IOC lifecycle automated (ingest, enrich, score, deploy, expire); analyst attention on exceptions only | F17: =IF(E17="","",E17)
B18: T0-Q4 | C18: Indicator of Compromise Handling | D18: Are all inbound IOCs captured in a tracking system (TIP, ticket queue, or equivalent) rather than email? | F18: =IF(E18="Yes",3,IF(E18="No",1,""))
B19: T0-Q5 | C19: Intelligence Source Inventory | D19: Rate the completeness of your intelligence source inventory. 1 — No written source list; subscribed feeds live in individual analyst heads 2 — Spreadsheet or wiki list exists; <50% of entries have an owner and last-review date 3 — >=90% of sources have owner, purpose, cost, renewal, and review date; inventory reviewed at least annually 4 — Sources rated for quality (CRAAP or Admiralty-style); low-value sources retired; gap list maintained 5 — Source ROI measured against PIRs; changes tied to explicit business cases; cost-per-useful-product tracked | F19: =IF(E19="","",E19)
B20: T0-Q6 | C20: Stakeholder Awareness and Access | D20: Rate how well your stakeholder teams (SOC, DE, IR, VM) can engage CTI. 1 — Stakeholders cannot consistently name a CTI contact; engagement is person-dependent 2 — Informal relationships with 1-2 stakeholder teams; no recurring cadence 3 — Named POCs published for SOC, DE, IR; at least one recurring cadence in place 4 — >=4 recurring stakeholder cadences with agendas; RFI path used and logged 5 — Annual NPS (or equivalent) measured; cadence and services adjusted based on feedback; new stakeholders onboarded via defined intake | F20: =IF(E20="","",E20)
B21: TIER 1: BASIC
B22: CTI operates from written Priority Intelligence Requirements, uses a consistent product template with BLUF structure, applies calibrated probability language, and rates sources for reliability.
B23: T1-Q1 | C23: Priority Intelligence Requirements (PIRs) | D23: Rate the maturity of your Priority Intelligence Requirements (PIRs). 1 — No PIRs; collection driven by whatever catches analyst attention 2 — Legacy PIR deck exists but not reviewed in >12 months; <30% of current collection traces to it 3 — 6-12 current PIRs documented, each with named stakeholder and business question; reviewed within the last 12 months 4 — >=80% of PIRs decomposed into Specific Intelligence Requirements (SIRs); PIR coverage rate tracked 5 — Documented PIR lifecycle with stakeholder workshops, risk-register alignment, retirement list, and quarterly metrics | F23: =IF(E23="","",E23)
B24: T1-Q2 | C24: Priority Intelligence Requirements (PIRs) | D24: Does every major CTI product cite at least one PIR it supports? | F24: =IF(E24="Yes",3,IF(E24="No",1,""))
B25: T1-Q3 | C25: Product Template and BLUF Structure | D25: Rate the consistency of your product template and use of BLUF structure. 1 — No template; reports vary widely; BLUF absent or buried 2 — Template exists but <60% of products conform; BLUF often confused with executive summary 3 — >=90% of products conform; BLUF is the first paragraph with key judgments; distinct evidence/analysis/implications sections 4 — Template includes alternatives considered and customer-relevance; version-controlled; analyst-reviewed changes 5 — Template benchmarked against ICD 203; peer review catches deviations; trained competency | F25: =IF(E25="","",E25)
B26: T1-Q4 | C26: Calibrated Language and Source Reliability | D26: Rate your use of calibrated probability language and source reliability ratings. 1 — No calibrated scale; no source reliability ratings; confidence is implicit 2 — Team aware of calibrated language and Admiralty/NATO ratings; <50% of judgments apply them 3 — >=90% of key judgments use calibrated probability language; >=90% of sources have reliability/credibility ratings 4 — Template enforces calibrated language and source rating; peer review checklist references ICD 203 5 — Forecast calibration measured (Brier score or equivalent); miscalibration drives retraining | F26: =IF(E26="","",E26)
B27: T1-Q5 | C27: Calibrated Language and Source Reliability | D27: Has the team adopted a published calibrated probability scale (e.g., ODNI 8-level)? | F27: =IF(E27="Yes",3,IF(E27="No",1,""))
B28: T1-Q6 | C28: Collection Management Framework (CMF) | D28: Rate the maturity of your Collection Management Framework (CMF). 1 — No CMF; no mapping from sources to PIRs 2 — Draft CMF exists in spreadsheet form; <30% of sources mapped to PIRs 3 — Documented CMF with >=80% of sources mapped to PIRs/SIRs; coverage gaps visible 4 — Quarterly CMF review; CRAAP ratings on >=80% of sources; passive-vs-active collection tagged 5 — Per-PIR collection plan; source cost/coverage/ROI tracked; defensible to leadership and auditors | F28: =IF(E28="","",E28)
B29: TIER 2: OPERATIONAL
B30: A Threat Intelligence Platform (or equivalent) is in place; IOC flow to SIEM and EDR is automated; Detection Engineering handoff is scheduled; CTI partners with the dedicated Threat Hunting team on a cadence; and Incident Response is enriched with CTI context on every incident.
B31: T2-Q1 | C31: Threat Intelligence Platform and IOC Pipeline | D31: Rate the maturity of your Threat Intelligence Platform (TIP) and IOC pipeline. 1 — No TIP; IOCs in spreadsheets, emails, or hand-updated SIEM watchlists 2 — TIP deployed but underutilized; <50% of feeds ingested; manual SIEM push 3 — >=5 feeds ingested via STIX/TAXII or API; SIEM push automated; IOC expiration policy configured 4 — Closed-loop SOC feedback adjusts source fidelity scoring; high-fidelity indicators can trigger SOAR blocking 5 — TIP is the single source of truth across SIEM/EDR/SOAR/firewalls; pipeline SLOs monitored; analyst pivoting standard | F31: =IF(E31="","",E31)
B32: T2-Q2 | C32: Threat Intelligence Platform and IOC Pipeline | D32: Is a Threat Intelligence Platform deployed and actively used by analysts? | F32: =IF(E32="Yes",3,IF(E32="No",1,""))
B33: T2-Q3 | C33: Detection Engineering Handoff | D33: Rate the maturity of the CTI-to-Detection-Engineering handoff. 1 — Ad-hoc interaction; verbal or email requests; no backlog; no provenance on shipped rules 2 — <1 formal request per month; no cadence; no template 3 — >=1 CTI-to-DE cadence per month; standard request template (threat, TTP, ATT&CK ID, suggested logic); backlog visible to both teams 4 — CTI-driven detections tagged in the Detection-as-Code repo; hit rate and FP rate measured against CTI rules 5 — Lead time from CTI request to deployed detection measured; ATT&CK coverage map auto-generated; CTI influences DE roadmap | F33: =IF(E33="","",E33)
B34: T2-Q4 | C34: Collaboration with the Threat Hunting Team | D34: Rate the maturity of CTI's partnership with the Threat Hunting team. 1 — No structured relationship; CTI does not feed hunt ideas; hunt findings do not flow back 2 — Informal, ad-hoc interaction (<1 structured handoff per month); occasional IOC or actor-name email 3 — Recurring CTI-to-Hunt cadence (>=monthly); CTI submits hunt hypothesis abstracts scoped against PIRs and ATT&CK; hunts target Pyramid-of-Pain TTPs and tools 4 — Hunt findings flow back and update threat profile, PIRs, and CMF; CTI provides enriched intel packages (actor, Diamond Model, ATT&CK Navigator layers) to scope hunts 5 — CTI-Hunt partnership measured (% hunts sourced by CTI, % producing downstream artifact, yield YoY); retrospectives on cadence | F34: =IF(E34="","",E34)
B35: T2-Q5 | C35: Collaboration with the Threat Hunting Team | D35: Does a recurring (at least monthly) working cadence exist between CTI and the Threat Hunting team? | F35: =IF(E35="Yes",3,IF(E35="No",1,""))
B36: T2-Q6 | C36: Incident Response Enrichment | D36: Rate the maturity of CTI enrichment for Incident Response. 1 — CTI involved in <30% of major incidents; IR analysts self-serve for context 2 — Ad-hoc enrichment when asked; not tracked; no SLA 3 — >=90% of high-severity incidents enriched (actor, TTPs, campaign, prior observations); named CTI on-call liaison 4 — Automated enrichment via TIP/SOAR on ticket creation; ATT&CK mapping on >=80% of IR cases; Diamond Model applied 5 — Post-incident CTI output drives PIRs, detection backlog, and threat profile; MTTD/MTTR attribution measured where possible | F36: =IF(E36="","",E36)
B37: TIER 3: ADVANCED
B38: CTI produces specialized intelligence for telco-context stakeholders (Vulnerability Management, Fraud, Third-Party Risk) and delivers a recurring Cyber Threat Landscape product at strategic/operational/tactical tiers.
B39: T3-Q1 | C39: Vulnerability and Exploit Intelligence | D39: Rate the maturity of CTI support to Vulnerability Management for telco stack. 1 — No CTI input to VM prioritization; VM prioritizes on CVSS alone 2 — Reactive alerts on viral CVEs only; no cadence; no telco-stack tagging 3 — Recurring VM brief (bi-weekly or monthly); CVEs tagged for relevance to telco tech stack (RAN, core, transport, OSS/BSS, hyperscaler, CPE) 4 — EPSS, exploit-in-the-wild observation, and underground chatter integrated; telco protocol vulns (SS7, Diameter, GTP, 5G) tracked; CTI modifiers feed VM prioritization 5 — CTI-driven score is the primary VM signal for externally-facing assets; predictive advisories issued where responsible; post-patch verification tracked | F39: =IF(E39="","",E39)
B40: T3-Q2 | C40: Telco Fraud Intelligence | D40: Rate the maturity of CTI support to the Fraud team (smishing, SIM swap, ATO, brand). 1 — No Fraud engagement 2 — Occasional sharing of smishing samples or actor names; no cadence; no partnership 3 — Recurring Fraud cadence covering smishing kits, SIM swap, ATO tooling, number-porting abuse, and brand impersonation; RFI intake defined 4 — Automated brand-impersonation monitoring (domain squatting, malvertising, lookalike apps); smishing kit repository; indicators flow to SOC and Fraud detection 5 — Cross-carrier intelligence sharing on fraud actors; takedown cadence in place; fraud prevention dollar impact attributed where possible | F40: =IF(E40="","",E40)
B41: T3-Q3 | C41: Telco Fraud Intelligence | D41: Is there a recurring cadence between CTI and the Fraud team? | F41: =IF(E41="Yes",3,IF(E41="No",1,""))
B42: T3-Q4 | C42: Third-Party and Supply-Chain Intelligence | D42: Rate the maturity of CTI support to Third-Party Risk Management. 1 — No third-party monitoring 2 — Reactive on major vendor breaches only; no monitored vendor list 3 — Top 20-50 third parties monitored (equipment vendors, roaming partners, CPE suppliers, cloud/SaaS, interconnect carriers); recurring TPRM brief; breach intake path documented 4 — TPRM-platform integration (or structured handoff) with automated vendor-breach alerting; supply-chain IOC tracking; geopolitical shifts surfaced 5 — CTI contributes to M&A / procurement due diligence; roaming and interconnect partner risks inform network segmentation decisions | F42: =IF(E42="","",E42)
B43: T3-Q5 | C43: Cyber Threat Landscape Reporting | D43: Rate the maturity of your recurring Cyber Threat Landscape (CTL) product. 1 — No recurring CTL product 2 — Irregular one-off reports; <4 per year; no consistent structure or tiering 3 — CTL delivered at least quarterly on a published schedule; ENISA-style methodology; tactical / operational / strategic tiering distinguishable 4 — Tiered audiences defined (CISO, SOC, VM); stakeholder feedback solicited and logged; trend view across editions maintained 5 — Strategic CTL drives CISO/CIO decisions; operational CTL drives hunt and detection backlogs; annual retrospective on forecast hits and misses | F43: =IF(E43="","",E43)
B44: TIER 4: LEADING
B45: Strategic intelligence reaches the CISO and board on cadence; Structured Analytic Techniques are standard practice; CTI-attributable outcomes are measured; forecast calibration is tracked.
B46: T4-Q1 | C46: Strategic Intelligence to Leadership | D46: Rate the maturity of strategic intelligence delivered to CISO and senior leadership. 1 — No strategic briefing cadence with CISO or senior leaders 2 — Occasional ad-hoc contribution to CISO decks; no standing product 3 — Quarterly strategic brief produced in non-technical language with clear enterprise implications 4 — Strategic brief informs risk register updates and security-investment decisions; Canadian regulatory context (CRTC, CCCS, Bill C-26) synthesized 5 — Standing input to annual enterprise strategy and board-level cyber-risk discussions; products survive external / regulator scrutiny | F46: =IF(E46="","",E46)
B47: T4-Q2 | C47: Structured Analytic Techniques (SATs) | D47: Rate your team's use of Structured Analytic Techniques (ACH, Key Assumptions Check, Pre-Mortem, etc.). 1 — Analysts unfamiliar with SATs; no SAT training or artifacts 2 — Awareness of SATs conceptually; <10% of major products show SAT application 3 — >=80% of major products (high-impact assessments, attribution claims, strategic forecasts) show explicit SAT application 4 — Team repertoire of >=4 SATs; SAT selection guided by the analytic question; peer review checks SAT appropriateness 5 — SATs are a trained competency; bias countermeasures are part of the culture; annual SAT refresher; retrospectives on SAT-driven decisions | F47: =IF(E47="","",E47)
B48: T4-Q3 | C48: Attributable Outcomes and Impact Metrics | D48: Rate your ability to attribute outcomes (detections, hunts, incidents, decisions) to CTI products. 1 — No outcome attribution 2 — Anecdotal success stories only; not systematically captured 3 — Outcome log maintained; >=5 outcomes per quarter (detections, hunts, incidents, risk-register changes, procurement decisions) 4 — Outcome KPIs (% detections attributable to CTI, MTTR reduction, fraud $ prevented, vendor changes driven by CTI) in quarterly leadership pack 5 — Outcome data drives budget and headcount decisions; ROI metric published; investment-vs-outcome ratios tracked | F48: =IF(E48="","",E48)
B49: T4-Q4 | C49: Attributable Outcomes and Impact Metrics | D49: Does CTI report outcome metrics to leadership at least quarterly? | F49: =IF(E49="Yes",4,IF(E49="No",1,""))
B50: T4-Q5 | C50: Forecast Calibration | D50: Rate the maturity of forecast calibration tracking for your analytic products. 1 — Forecasts are not tracked; no retrospective check on accuracy 2 — Occasional retrospective on major assessments only 3 — All forecasts with confidence statements logged with resolution criteria; quarterly review of resolved forecasts 4 — Calibration score (Brier or equivalent) computed; errors drive retraining or process changes 5 — Calibration reported alongside output metrics; year-over-year improvement target committed and tracked | F50: =IF(E50="","",E50)
B52: ENRICHMENT DIMENSIONS — Tradecraft and Governance
B53: Cross-cutting tradecraft and governance factors. They contribute to the overall score but do not affect TIBMM tier determination.
B54: ID | C54: Criterion | D54: Question | E54: Answer | F54: Score
B55: TRADECRAFT AND ANALYST CAPABILITY
B56: Cross-cutting analytic quality factors.
B57: E1-Q1 | C57: ICD 203 Analytic Standards Adherence | D57: Rate your team's adherence to ICD 203 analytic tradecraft standards. 1 — Team unfamiliar with ICD 203 / SANS playbook-equivalent standards 2 — Lead aware; no analyst-level training; no consistent application 3 — All analysts trained on ICD 203 (or SANS-equivalent); products spot-checked for adherence 4 — Peer review checklist uses ICD 203 standards 1-7 as pass gates 5 — All nine ICD 203 standards measured or reviewed; standard 8 tracked via forecast calibration | F57: =IF(E57="","",E57)
B58: E1-Q2 | C58: Framework Literacy (ATT&CK, Diamond, Kill Chain) | D58: Rate team fluency with MITRE ATT&CK, the Diamond Model, and the Cyber Kill Chain. 1 — <50% of analysts confidently use ATT&CK, Diamond, or Kill Chain in analysis 2 — ATT&CK referenced occasionally; Diamond and Kill Chain rarely used 3 — >=90% of behavioral products use ATT&CK tactic/technique IDs; Diamond/Kill Chain used where appropriate 4 — ATT&CK Navigator layers published for major campaigns/actors; Diamond diagrams in incident and campaign reports 5 — Live ATT&CK coverage heatmap linked to PIRs; framework outputs feed detection coverage mapping and hunt prioritization | F58: =IF(E58="","",E58)
B59: E1-Q3 | C59: Peer Review Process | D59: Rate the maturity of your peer review process for finished products. 1 — No peer review; analysts self-publish 2 — Informal peer review; <50% of products reviewed 3 — >=90% of finished products peer-reviewed; named reviewer; written review criteria 4 — Peer review uses a checklist tied to ICD 203, template, calibrated language, and source rating; review SLA tracked 5 — Peer review findings drive training and template improvements; cross-team review (with DE or peer CTI teams) on cadence | F59: =IF(E59="","",E59)
B60: E1-Q4 | C60: Peer Review Process | D60: Are all finished intelligence products peer-reviewed before release? | F60: =IF(E60="Yes",3,IF(E60="No",1,""))
B61: GOVERNANCE, LEGAL, ETHICS, AND IMPROVEMENT
B62: Program hygiene that keeps the function defensible to regulators, partners, and internal audit — and ensures it improves over time rather than drifting.
B63: E2-Q1 | C63: Legal and Regulatory Review (PIPEDA, CASL, CRTC) | D63: Rate the maturity of legal / regulatory review over CTI sources and techniques (PIPEDA, CASL, CRTC, Bill C-26 CCSPA). 1 — No review of sources or techniques against Canadian legal/regulatory constraints 2 — Awareness-level only; analyst self-check; no formal process 3 — Sources screened against PIPEDA for personal-information collection; active-collection techniques have documented legal sign-off 4 — Annual review with privacy/legal partners; written and approved passive-vs-active collection posture 5 — Regulatory alignment tracked (CRTC expectations, Bill C-26 CCSPA obligations); CTI participates in breach-notification and regulatory-reporting workflows | F63: =IF(E63="","",E63)
B64: E2-Q2 | C64: External Sharing and Trust-Group Participation | D64: Rate your team's participation in external sharing communities (CCTX, trust groups, CCCS partnership). 1 — No memberships 2 — Passive membership in 1-2 groups; no shares in the last 12 months 3 — Active membership in CCTX and/or relevant trust groups; shares per quarter; TLP and sharing constraints understood 4 — Material bi-directional sharing (>=1 share per month); partner-attributable value captured 5 — Recognized sector contributor; leadership role held (working-group chair, framework author, or similar) | F64: =IF(E64="","",E64)
B65: E2-Q3 | C65: Continuous Improvement and Self-Assessment | D65: Rate the maturity of your CTI self-assessment and continuous improvement cadence. 1 — No self-assessment in the last 24 months 2 — One-off maturity assessment; not repeated 3 — TIBMM (or equivalent) run annually; gap list maintained 4 — Bi-annual full TIBMM plus quarterly KPI check-ins; gaps tied to a roadmap with owners and target dates 5 — TIBMM scores reported to leadership alongside operational KPIs; year-over-year trend visible; improvement targets committed | F65: =IF(E65="","",E65)

Sheet Results Dashboard
A1: TIBMM Assessment Results
A2: =" "&Assessment!D4
B5: Overall Maturity Score | D5: Achieved TIBMM Tier | F5: Completion
B6: =IF(COUNT(D13,D14,D15,D16,D18,D19,D20,D21,D23,D24,D25,D26,D28,D29,D30,D31,D33,D34,D35,D36,D42,D43,D44,D46,D47,D48)=0,"",ROUND(AVERAGE(D13,D14,D15,D16,D18,D19,D20,D21,D23,D24,D25,D26,D28,D29,D30,D31,D33,D34,D35,D36,D42,D43,D44,D46,D47,D48),2)&" / 5.0") | D6: =IF(AND(AND(ISNUMBER(D13),D13>=3,ISNUMBER(D14),D14>=3,ISNUMBER(D15),D15>=3,ISNUMBER(D16),D16>=3),AND(ISNUMBER(D18),D18>=3,ISNUMBER(D19),D19>=3,ISNUMBER(D20),D20>=3,ISNUMBER(D21),D21>=3),AND(ISNUMBER(D23),D23>=3,ISNUMBER(D24),D24>=3,ISNUMBER(D25),D25>=3,ISNUMBER(D26),D26>=3),AND(ISNUMBER(D28),D28>=3,ISNUMBER(D29),D29>=3,ISNUMBER(D30),D30>=3,ISNUMBER(D31),D31>=3),AND(ISNUMBER(D33),D33>=3,ISNUMBER(D34),D34>=3,ISNUMBER(D35),D35>=3,ISNUMBER(D36),D36>=3)),"Tier 4: Leading",IF(AND(AND(ISNUMBER(D13),D13>=3,ISNUMBER(D14),D14>=3,ISNUMBER(D15),D15>=3,ISNUMBER(D16),D16>=3),AND(ISNUMBER(D18),D18>=3,ISNUMBER(D19),D19>=3,ISNUMBER(D20),D20>=3,ISNUMBER(D21),D21>=3),AND(ISNUMBER(D23),D23>=3,ISNUMBER(D24),D24>=3,ISNUMBER(D25),D25>=3,ISNUMBER(D26),D26>=3),AND(ISNUMBER(D28),D28>=3,ISNUMBER(D29),D29>=3,ISNUMBER(D30),D30>=3,ISNUMBER(D31),D31>=3)),"Tier 3: Advanced",IF(AND(AND(ISNUMBER(D13),D13>=3,ISNUMBER(D14),D14>=3,ISNUMBER(D15),D15>=3,ISNUMBER(D16),D16>=3),AND(ISNUMBER(D18),D18>=3,ISNUMBER(D19),D19>=3,ISNUMBER(D20),D20>=3,ISNUMBER(D21),D21>=3),AND(ISNUMBER(D23),D23>=3,ISNUMBER(D24),D24>=3,ISNUMBER(D25),D25>=3,ISNUMBER(D26),D26>=3)),"Tier 2: Operational",IF(AND(AND(ISNUMBER(D13),D13>=3,ISNUMBER(D14),D14>=3,ISNUMBER(D15),D15>=3,ISNUMBER(D16),D16>=3),AND(ISNUMBER(D18),D18>=3,ISNUMBER(D19),D19>=3,ISNUMBER(D20),D20>=3,ISNUMBER(D21),D21>=3)),"Tier 1: Basic",IF(AND(AND(ISNUMBER(D13),D13>=3,ISNUMBER(D14),D14>=3,ISNUMBER(D15),D15>=3,ISNUMBER(D16),D16>=3)),"Tier 0: Foundation","Below Foundation"))))) | F6: =COUNTA(Assessment!E15,Assessment!E16,Assessment!E17,Assessment!E18,Assessment!E19,Assessment!E20,Assessment!E23,Assessment!E24,Assessment!E25,Assessment!E26,Assessment!E27,Assessment!E28,Assessment!E31,Assessment!E32,Assessment!E33,Assessment!E34,Assessment!E35,Assessment!E36,Assessment!E39,Assessment!E40,Assessment!E41,Assessment!E42,Assessment!E43,Assessment!E46,Assessment!E47,Assessment!E48,Assessment!E49,Assessment!E50,Assessment!E57,Assessment!E58,Assessment!E59,Assessment!E60,Assessment!E63,Assessment!E64,Assessment!E65)&" / 35"
B8: =IF(D6="","",IF(D6="Tier 4: Leading","The CTI function has achieved Tier 4 (Leading) — the highest TIBMM tier. Strategic intelligence reaches the CISO and board, SATs are standard practice, attributable outcomes are reported to leadership, and forecast calibration is measured. Focus on sustaining this posture, contributing to the telco-sector intelligence community, and using outcome data at budget review.",IF(D6="Tier 3: Advanced","The CTI function has achieved Tier 3 (Advanced). Stakeholder-specific intelligence products (VM, Fraud, TPRM, CTL) are running on cadence and influencing downstream decisions. To advance to Tier 4, produce a standing strategic brief for the CISO, apply Structured Analytic Techniques to major products, track CTI-attributable outcomes quantitatively, and measure forecast calibration.",IF(D6="Tier 2: Operational","The CTI function has achieved Tier 2 (Operational). TIP + IOC pipeline, DE handoff, CTI-Hunt partnership, and IR enrichment are running on a cadence. To advance to Tier 3, stand up recurring products for Vulnerability Management (EPSS + telco-stack tagging), Fraud (smishing, SIM swap, brand), and Third-Party Risk, and publish a tiered Cyber Threat Landscape report.",IF(D6="Tier 1: Basic","The CTI function has achieved Tier 1 (Basic). PIRs and the tradecraft floor (BLUF, calibrated language, source rating, CMF) are in place. To advance to Tier 2, deploy a Threat Intelligence Platform with automated IOC flow to the SIEM, formalize the CTI→Detection-Engineering handoff, establish a working cadence with the Threat Hunting team, and enrich every major incident with CTI context.",IF(D6="Tier 0: Foundation","The CTI function has achieved Tier 0 (Foundation). The role is documented, IOCs are handled consistently, sources are inventoried, and stakeholders know how to engage. To reach Tier 1, publish Priority Intelligence Requirements, adopt a BLUF product template, require calibrated probability language and source reliability ratings, and build a Collection Management Framework.","The CTI function has not yet achieved Tier 0 (Foundation). One or more foundational criteria — charter/service catalog, IOC handling, source inventory, or stakeholder touchpoints — score below the Defined level (3.0). Focus on documenting what CTI delivers and to whom, and on establishing a minimally disciplined IOC process, before pursuing higher tiers."))))))
B10: TIBMM CORE ASSESSMENT
C11: Category / Criterion | D11: Score | E11: Level | F11: Status
C12: Foundation | D12: =IF(COUNT(D13,D14,D15,D16)=0,"",AVERAGE(D13,D14,D15,D16)) | E12: =IF(D12="","",IF(D12>=4.5,"Optimized",IF(D12>=3.5,"Managed",IF(D12>=2.5,"Defined",IF(D12>=1.5,"Repeatable","Initial"))))) | F12: =IF(D12="","",IF(D12>=3,"✓ Pass","✗ Below Target"))
C13: Mission, Charter, and Service Catalog | D13: =IF(COUNT(Assessment!F15,Assessment!F16)=0,"",AVERAGE(Assessment!F15,Assessment!F16)) | E13: =IF(D13="","",IF(D13>=4.5,"Optimized",IF(D13>=3.5,"Managed",IF(D13>=2.5,"Defined",IF(D13>=1.5,"Repeatable","Initial"))))) | F13: =IF(D13="","",IF(D13>=3,"✓ Pass","✗ Below Target"))
C14: Indicator of Compromise Handling | D14: =IF(COUNT(Assessment!F17,Assessment!F18)=0,"",AVERAGE(Assessment!F17,Assessment!F18)) | E14: =IF(D14="","",IF(D14>=4.5,"Optimized",IF(D14>=3.5,"Managed",IF(D14>=2.5,"Defined",IF(D14>=1.5,"Repeatable","Initial"))))) | F14: =IF(D14="","",IF(D14>=3,"✓ Pass","✗ Below Target"))
C15: Intelligence Source Inventory | D15: =IF(COUNT(Assessment!F19)=0,"",AVERAGE(Assessment!F19)) | E15: =IF(D15="","",IF(D15>=4.5,"Optimized",IF(D15>=3.5,"Managed",IF(D15>=2.5,"Defined",IF(D15>=1.5,"Repeatable","Initial"))))) | F15: =IF(D15="","",IF(D15>=3,"✓ Pass","✗ Below Target"))
C16: Stakeholder Awareness and Access | D16: =IF(COUNT(Assessment!F20)=0,"",AVERAGE(Assessment!F20)) | E16: =IF(D16="","",IF(D16>=4.5,"Optimized",IF(D16>=3.5,"Managed",IF(D16>=2.5,"Defined",IF(D16>=1.5,"Repeatable","Initial"))))) | F16: =IF(D16="","",IF(D16>=3,"✓ Pass","✗ Below Target"))
C17: Basic | D17: =IF(COUNT(D18,D19,D20,D21)=0,"",AVERAGE(D18,D19,D20,D21)) | E17: =IF(D17="","",IF(D17>=4.5,"Optimized",IF(D17>=3.5,"Managed",IF(D17>=2.5,"Defined",IF(D17>=1.5,"Repeatable","Initial"))))) | F17: =IF(D17="","",IF(D17>=3,"✓ Pass","✗ Below Target"))
C18: Priority Intelligence Requirements (PIRs) | D18: =IF(COUNT(Assessment!F23,Assessment!F24)=0,"",AVERAGE(Assessment!F23,Assessment!F24)) | E18: =IF(D18="","",IF(D18>=4.5,"Optimized",IF(D18>=3.5,"Managed",IF(D18>=2.5,"Defined",IF(D18>=1.5,"Repeatable","Initial"))))) | F18: =IF(D18="","",IF(D18>=3,"✓ Pass","✗ Below Target"))
C19: Product Template and BLUF Structure | D19: =IF(COUNT(Assessment!F25)=0,"",AVERAGE(Assessment!F25)) | E19: =IF(D19="","",IF(D19>=4.5,"Optimized",IF(D19>=3.5,"Managed",IF(D19>=2.5,"Defined",IF(D19>=1.5,"Repeatable","Initial"))))) | F19: =IF(D19="","",IF(D19>=3,"✓ Pass","✗ Below Target"))
C20: Calibrated Language and Source Reliability | D20: =IF(COUNT(Assessment!F26,Assessment!F27)=0,"",AVERAGE(Assessment!F26,Assessment!F27)) | E20: =IF(D20="","",IF(D20>=4.5,"Optimized",IF(D20>=3.5,"Managed",IF(D20>=2.5,"Defined",IF(D20>=1.5,"Repeatable","Initial"))))) | F20: =IF(D20="","",IF(D20>=3,"✓ Pass","✗ Below Target"))
C21: Collection Management Framework (CMF) | D21: =IF(COUNT(Assessment!F28)=0,"",AVERAGE(Assessment!F28)) | E21: =IF(D21="","",IF(D21>=4.5,"Optimized",IF(D21>=3.5,"Managed",IF(D21>=2.5,"Defined",IF(D21>=1.5,"Repeatable","Initial"))))) | F21: =IF(D21="","",IF(D21>=3,"✓ Pass","✗ Below Target"))
C22: Operational | D22: =IF(COUNT(D23,D24,D25,D26)=0,"",AVERAGE(D23,D24,D25,D26)) | E22: =IF(D22="","",IF(D22>=4.5,"Optimized",IF(D22>=3.5,"Managed",IF(D22>=2.5,"Defined",IF(D22>=1.5,"Repeatable","Initial"))))) | F22: =IF(D22="","",IF(D22>=3,"✓ Pass","✗ Below Target"))
C23: Threat Intelligence Platform and IOC Pipeline | D23: =IF(COUNT(Assessment!F31,Assessment!F32)=0,"",AVERAGE(Assessment!F31,Assessment!F32)) | E23: =IF(D23="","",IF(D23>=4.5,"Optimized",IF(D23>=3.5,"Managed",IF(D23>=2.5,"Defined",IF(D23>=1.5,"Repeatable","Initial"))))) | F23: =IF(D23="","",IF(D23>=3,"✓ Pass","✗ Below Target"))
C24: Detection Engineering Handoff | D24: =IF(COUNT(Assessment!F33)=0,"",AVERAGE(Assessment!F33)) | E24: =IF(D24="","",IF(D24>=4.5,"Optimized",IF(D24>=3.5,"Managed",IF(D24>=2.5,"Defined",IF(D24>=1.5,"Repeatable","Initial"))))) | F24: =IF(D24="","",IF(D24>=3,"✓ Pass","✗ Below Target"))
C25: Collaboration with the Threat Hunting Team | D25: =IF(COUNT(Assessment!F34,Assessment!F35)=0,"",AVERAGE(Assessment!F34,Assessment!F35)) | E25: =IF(D25="","",IF(D25>=4.5,"Optimized",IF(D25>=3.5,"Managed",IF(D25>=2.5,"Defined",IF(D25>=1.5,"Repeatable","Initial"))))) | F25: =IF(D25="","",IF(D25>=3,"✓ Pass","✗ Below Target"))
C26: Incident Response Enrichment | D26: =IF(COUNT(Assessment!F36)=0,"",AVERAGE(Assessment!F36)) | E26: =IF(D26="","",IF(D26>=4.5,"Optimized",IF(D26>=3.5,"Managed",IF(D26>=2.5,"Defined",IF(D26>=1.5,"Repeatable","Initial"))))) | F26: =IF(D26="","",IF(D26>=3,"✓ Pass","✗ Below Target"))
C27: Advanced | D27: =IF(COUNT(D28,D29,D30,D31)=0,"",AVERAGE(D28,D29,D30,D31)) | E27: =IF(D27="","",IF(D27>=4.5,"Optimized",IF(D27>=3.5,"Managed",IF(D27>=2.5,"Defined",IF(D27>=1.5,"Repeatable","Initial"))))) | F27: =IF(D27="","",IF(D27>=3,"✓ Pass","✗ Below Target"))
C28: Vulnerability and Exploit Intelligence | D28: =IF(COUNT(Assessment!F39)=0,"",AVERAGE(Assessment!F39)) | E28: =IF(D28="","",IF(D28>=4.5,"Optimized",IF(D28>=3.5,"Managed",IF(D28>=2.5,"Defined",IF(D28>=1.5,"Repeatable","Initial"))))) | F28: =IF(D28="","",IF(D28>=3,"✓ Pass","✗ Below Target"))
C29: Telco Fraud Intelligence | D29: =IF(COUNT(Assessment!F40,Assessment!F41)=0,"",AVERAGE(Assessment!F40,Assessment!F41)) | E29: =IF(D29="","",IF(D29>=4.5,"Optimized",IF(D29>=3.5,"Managed",IF(D29>=2.5,"Defined",IF(D29>=1.5,"Repeatable","Initial"))))) | F29: =IF(D29="","",IF(D29>=3,"✓ Pass","✗ Below Target"))
C30: Third-Party and Supply-Chain Intelligence | D30: =IF(COUNT(Assessment!F42)=0,"",AVERAGE(Assessment!F42)) | E30: =IF(D30="","",IF(D30>=4.5,"Optimized",IF(D30>=3.5,"Managed",IF(D30>=2.5,"Defined",IF(D30>=1.5,"Repeatable","Initial"))))) | F30: =IF(D30="","",IF(D30>=3,"✓ Pass","✗ Below Target"))
C31: Cyber Threat Landscape Reporting | D31: =IF(COUNT(Assessment!F43)=0,"",AVERAGE(Assessment!F43)) | E31: =IF(D31="","",IF(D31>=4.5,"Optimized",IF(D31>=3.5,"Managed",IF(D31>=2.5,"Defined",IF(D31>=1.5,"Repeatable","Initial"))))) | F31: =IF(D31="","",IF(D31>=3,"✓ Pass","✗ Below Target"))
C32: Leading | D32: =IF(COUNT(D33,D34,D35,D36)=0,"",AVERAGE(D33,D34,D35,D36)) | E32: =IF(D32="","",IF(D32>=4.5,"Optimized",IF(D32>=3.5,"Managed",IF(D32>=2.5,"Defined",IF(D32>=1.5,"Repeatable","Initial"))))) | F32: =IF(D32="","",IF(D32>=3,"✓ Pass","✗ Below Target"))
C33: Strategic Intelligence to Leadership | D33: =IF(COUNT(Assessment!F46)=0,"",AVERAGE(Assessment!F46)) | E33: =IF(D33="","",IF(D33>=4.5,"Optimized",IF(D33>=3.5,"Managed",IF(D33>=2.5,"Defined",IF(D33>=1.5,"Repeatable","Initial"))))) | F33: =IF(D33="","",IF(D33>=3,"✓ Pass","✗ Below Target"))
C34: Structured Analytic Techniques (SATs) | D34: =IF(COUNT(Assessment!F47)=0,"",AVERAGE(Assessment!F47)) | E34: =IF(D34="","",IF(D34>=4.5,"Optimized",IF(D34>=3.5,"Managed",IF(D34>=2.5,"Defined",IF(D34>=1.5,"Repeatable","Initial"))))) | F34: =IF(D34="","",IF(D34>=3,"✓ Pass","✗ Below Target"))
C35: Attributable Outcomes and Impact Metrics | D35: =IF(COUNT(Assessment!F48,Assessment!F49)=0,"",AVERAGE(Assessment!F48,Assessment!F49)) | E35: =IF(D35="","",IF(D35>=4.5,"Optimized",IF(D35>=3.5,"Managed",IF(D35>=2.5,"Defined",IF(D35>=1.5,"Repeatable","Initial"))))) | F35: =IF(D35="","",IF(D35>=3,"✓ Pass","✗ Below Target"))
C36: Forecast Calibration | D36: =IF(COUNT(Assessment!F50)=0,"",AVERAGE(Assessment!F50)) | E36: =IF(D36="","",IF(D36>=4.5,"Optimized",IF(D36>=3.5,"Managed",IF(D36>=2.5,"Defined",IF(D36>=1.5,"Repeatable","Initial"))))) | F36: =IF(D36="","",IF(D36>=3,"✓ Pass","✗ Below Target"))
B38: ENRICHMENT DIMENSIONS
B39: Tradecraft and governance factors — do not affect TIBMM tier determination
C40: Category / Criterion | D40: Score | E40: Level | F40: Status
C41: Tradecraft and Analyst Capability | D41: =IF(COUNT(D42,D43,D44)=0,"",AVERAGE(D42,D43,D44)) | E41: =IF(D41="","",IF(D41>=4.5,"Optimized",IF(D41>=3.5,"Managed",IF(D41>=2.5,"Defined",IF(D41>=1.5,"Repeatable","Initial"))))) | F41: =IF(D41="","",IF(D41>=3,"✓ Pass","✗ Below Target"))
C42: ICD 203 Analytic Standards Adherence | D42: =IF(COUNT(Assessment!F57)=0,"",AVERAGE(Assessment!F57)) | E42: =IF(D42="","",IF(D42>=4.5,"Optimized",IF(D42>=3.5,"Managed",IF(D42>=2.5,"Defined",IF(D42>=1.5,"Repeatable","Initial"))))) | F42: =IF(D42="","",IF(D42>=3,"✓ Pass","✗ Below Target"))
C43: Framework Literacy (ATT&CK, Diamond, Kill Chain) | D43: =IF(COUNT(Assessment!F58)=0,"",AVERAGE(Assessment!F58)) | E43: =IF(D43="","",IF(D43>=4.5,"Optimized",IF(D43>=3.5,"Managed",IF(D43>=2.5,"Defined",IF(D43>=1.5,"Repeatable","Initial"))))) | F43: =IF(D43="","",IF(D43>=3,"✓ Pass","✗ Below Target"))
C44: Peer Review Process | D44: =IF(COUNT(Assessment!F59,Assessment!F60)=0,"",AVERAGE(Assessment!F59,Assessment!F60)) | E44: =IF(D44="","",IF(D44>=4.5,"Optimized",IF(D44>=3.5,"Managed",IF(D44>=2.5,"Defined",IF(D44>=1.5,"Repeatable","Initial"))))) | F44: =IF(D44="","",IF(D44>=3,"✓ Pass","✗ Below Target"))
C45: Governance, Legal, Ethics, and Improvement | D45: =IF(COUNT(D46,D47,D48)=0,"",AVERAGE(D46,D47,D48)) | E45: =IF(D45="","",IF(D45>=4.5,"Optimized",IF(D45>=3.5,"Managed",IF(D45>=2.5,"Defined",IF(D45>=1.5,"Repeatable","Initial"))))) | F45: =IF(D45="","",IF(D45>=3,"✓ Pass","✗ Below Target"))
C46: Legal and Regulatory Review (PIPEDA, CASL, CRTC) | D46: =IF(COUNT(Assessment!F63)=0,"",AVERAGE(Assessment!F63)) | E46: =IF(D46="","",IF(D46>=4.5,"Optimized",IF(D46>=3.5,"Managed",IF(D46>=2.5,"Defined",IF(D46>=1.5,"Repeatable","Initial"))))) | F46: =IF(D46="","",IF(D46>=3,"✓ Pass","✗ Below Target"))
C47: External Sharing and Trust-Group Participation | D47: =IF(COUNT(Assessment!F64)=0,"",AVERAGE(Assessment!F64)) | E47: =IF(D47="","",IF(D47>=4.5,"Optimized",IF(D47>=3.5,"Managed",IF(D47>=2.5,"Defined",IF(D47>=1.5,"Repeatable","Initial"))))) | F47: =IF(D47="","",IF(D47>=3,"✓ Pass","✗ Below Target"))
C48: Continuous Improvement and Self-Assessment | D48: =IF(COUNT(Assessment!F65)=0,"",AVERAGE(Assessment!F65)) | E48: =IF(D48="","",IF(D48>=4.5,"Optimized",IF(D48>=3.5,"Managed",IF(D48>=2.5,"Defined",IF(D48>=1.5,"Repeatable","Initial"))))) | F48: =IF(D48="","",IF(D48>=3,"✓ Pass","✗ Below Target"))

Sheet Tier Scores Chart
A1: TIBMM Tier Scores
A2: Average score per TIBMM core tier (target: 3.0)
B4: Tier | C4: Score
B5: Foundation | C5: ='Results Dashboard'!D12
B6: Basic | C6: ='Results Dashboard'!D17
B7: Operational | C7: ='Results Dashboard'!D22
B8: Advanced | C8: ='Results Dashboard'!D27
B9: Leading | C9: ='Results Dashboard'!D32

Sheet Readiness Chart
A1: Tradecraft & Governance Readiness
A2: Enrichment dimensions — do not affect TIBMM tier determination
B4: Dimension | C4: Score
B5: Tradecraft and Analyst Capability | C5: ='Results Dashboard'!D41
B6: Governance, Legal, Ethics, and Improvement | C6: ='Results Dashboard'!D45

Sheet Rubric Reference
A1: TIBMM Rubric Reference
A3: TIBMM CORE TIERS
A4: Tier 0: Foundation
A5: The CTI function exists as a distinct capability with a known scope. Someone reads threat reports, someone handles IOCs, and stakeholders know CTI is here. Without these foundations, every higher tier is cosmetic.
A6: Mission, Charter, and Service Catalog
A7: Level | B7: Description | C7: Quantitative Measure
A8: 1 — Initial | B8: No documented mission, charter, or service catalog. CTI exists as a title without a defined scope; stakeholders cannot consistently describe what the team delivers. | C8: No written charter; stakeholder descriptions diverge significantly.
A9: 2 — Repeatable | B9: An informal description of CTI's role exists (email thread, wiki page) but is out of date, not signed off, and not socialized. | C9: Informal 1-page description exists; <30% of named stakeholders have seen it.
A10: 3 — Defined | B10: A current CTI charter, mission, and service catalog are documented, approved by the SOC/Security leader, and socialized to named stakeholders (SOC, DE, IR at minimum). | C10: Charter approved within last 12 months; service catalog lists >=3 service types.
A11: 4 — Managed | B11: Charter and catalog are reviewed annually with stakeholder input. Service catalog maps to stakeholder RACI; requests flow through a documented intake. | C11: Annual review on calendar; RACI defined; intake queue in ticketing system.
A12: 5 — Optimized | B12: Charter is a living artifact. Service catalog is instrumented — usage per service type is measured and feeds the next review. Charter referenced in budget and headcount conversations. | C12: Usage metrics per service type reported quarterly to leadership.
A14: Indicator of Compromise Handling
A15: Level | B15: Description | C15: Quantitative Measure
A16: 1 — Initial | B16: IOCs arrive via email, chat, or vendor portal and are handled ad-hoc by whoever notices. No triage, no enrichment, no routing convention. | C16: No IOC queue; no record of IOCs acted on in the last 90 days.
A17: 2 — Repeatable | B17: IOCs are forwarded to SOC/threat hunting manually on a best-effort basis. Some informal triage — at least obvious false positives are filtered. | C17: >0 but no SLA; <50% of IOCs are enriched before handoff.
A18: 3 — Defined | B18: IOCs are triaged against a documented process (source, context, confidence), enriched where useful, and routed to a named downstream owner (SIEM watchlist, EDR, firewall, hunt queue). | C18: Documented triage SOP; >=80% of IOCs carry source + confidence + disposition.
A19: 4 — Managed | B19: IOC handling is tracked in a TIP or ticketing system. Provenance, TLP, expiration, and disposition are recorded. Stakeholder feedback (true/false positive) is captured. | C19: TIP or ticket-based tracking; >=90% capture disposition; feedback rate measured.
A20: 5 — Optimized | B20: IOC handling is largely automated end-to-end: ingestion, enrichment, scoring, deployment, expiration, and feedback. Analyst time is spent on non-automatable judgment calls. | C20: >=80% of IOC lifecycle automated; analyst review focused on exceptions only.
A22: Intelligence Source Inventory
A23: Level | B23: Description | C23: Quantitative Measure
A24: 1 — Initial | B24: No list of subscribed feeds or sources exists. Knowledge of what the team reads lives in individual analyst heads; turnover would lose most of it. | C24: No written source list.
A25: 2 — Repeatable | B25: A basic list exists (spreadsheet or wiki) naming feeds and OSINT sources the team uses, but ownership, cost, renewal date, and purpose are missing or stale. | C25: List exists; <50% of entries have owner + last-review date.
A26: 3 — Defined | B26: A source inventory is maintained with name, type (OSINT, commercial, ISAC, government), owner, cost, renewal date, and short purpose statement. Reviewed at least annually. | C26: >=90% of sources have owner + purpose + review date.
A27: 4 — Managed | B27: Sources are evaluated for quality using a lightweight framework (CRAAP or Admiralty-style rating). Low-value sources are retired. Gaps against stakeholder needs are documented. | C27: Documented source quality ratings; >=1 retirement or addition per year based on ROI.
A28: 5 — Optimized | B28: Source ROI is measured against Priority Intelligence Requirements. Source changes are tied to explicit business cases. Cost-per-useful-product is tracked. | C28: Source ROI metric tracked; inventory cross-referenced to PIRs.
A30: Stakeholder Awareness and Access
A31: Level | B31: Description | C31: Quantitative Measure
A32: 1 — Initial | B32: Stakeholder teams (SOC, Detection Engineering, Incident Response) cannot consistently name a CTI contact or describe how to request support. Engagement depends on individual relationships. | C32: No stakeholder map; engagement is person-dependent.
A33: 2 — Repeatable | B33: CTI has informal relationships with at least one named stakeholder team (typically SOC or IR). Ad-hoc meetings occur but are not scheduled. | C33: 1-2 stakeholder teams engaged; no recurring meeting cadence.
A34: 3 — Defined | B34: Named CTI points-of-contact are published for each stakeholder team (SOC, DE, IR at minimum). Recurring check-ins exist with at least one stakeholder. | C34: >=3 stakeholder teams have named POC; >=1 recurring cadence in place.
A35: 4 — Managed | B35: Recurring cadence with all primary stakeholders (SOC, DE, IR, VM). Each cadence has a documented agenda and an owner. Intake and RFI paths are known and used. | C35: >=4 recurring cadences; agendas archived; RFIs logged.
A36: 5 — Optimized | B36: Stakeholder satisfaction is measured (NPS or equivalent) on an annual cycle. CTI adjusts cadence, products, and services based on stakeholder feedback. New stakeholders are onboarded via a defined intake. | C36: Annual NPS survey; documented onboarding; changes traceable to feedback.
A38: Tier 1: Basic
A39: CTI operates from written Priority Intelligence Requirements, uses a consistent product template with BLUF structure, applies calibrated probability language, and rates sources for reliability. This is the analytic tradecraft floor required before higher tiers become meaningful.
A40: Priority Intelligence Requirements (PIRs)
A41: Level | B41: Description | C41: Quantitative Measure
A42: 1 — Initial | B42: No PIRs exist. Collection and analysis are driven by whatever catches the analyst's eye or whatever a stakeholder asked for most recently. | C42: Zero written PIRs.
A43: 2 — Repeatable | B43: A legacy PIR deck exists but has not been reviewed in >12 months. Most current collection cannot be traced back to it. | C43: Stale PIRs; <30% of collection traceable to them.
A44: 3 — Defined | B44: A current set of 6-12 PIRs is documented, each with a named stakeholder and a business question. Reviewed at least annually with stakeholder input. | C44: 6-12 PIRs, each with stakeholder + question; <=12 months since last review.
A45: 4 — Managed | B45: PIRs are decomposed into Specific Intelligence Requirements (SIRs). Coverage against PIRs is measured. Gaps are tracked and addressed. | C45: >=80% of PIRs decomposed to SIRs; PIR coverage rate tracked.
A46: 5 — Optimized | B46: PIR development follows a documented process with stakeholder workshops, risk-register alignment, and explicit retirement of expired PIRs. PIR lifecycle metrics reported to leadership. | C46: Documented PIR lifecycle; retirement list; quarterly metric report.
A48: Product Template and BLUF Structure
A49: Level | B49: Description | C49: Quantitative Measure
A50: 1 — Initial | B50: No product template. Reports vary widely in structure; BLUF is absent or buried. Analysts each produce their own format. | C50: No template; <20% of products begin with a key judgment.
A51: 2 — Repeatable | B51: A template exists but is inconsistently applied. BLUF is sometimes present but is frequently confused with an executive summary. | C51: Template exists; <60% of products conform.
A52: 3 — Defined | B52: All finished products conform to a template that begins with a BLUF (bottom line up front) with key judgments. Evidence, analysis, implications, and outlook are distinct sections. | C52: >=90% of products conform; BLUF is the first paragraph in every product.
A53: 4 — Managed | B53: Template includes alternatives considered and customer-relevance section. Template is version-controlled; changes go through analyst review. | C53: Template versioned; alternatives section present in >=80% of products.
A54: 5 — Optimized | B54: Template structure is a trained tradecraft expectation. Deviations are caught in peer review. Template is benchmarked against ICD 203 standards. | C54: ICD 203 mapping documented; peer review catches template deviations.
A56: Calibrated Language and Source Reliability
A57: Level | B57: Description | C57: Quantitative Measure
A58: 1 — Initial | B58: Analysts use undefined probability terms ("possible", "probable", "likely") interchangeably. Sources are not rated. Confidence is implicit. | C58: No calibrated scale; no source reliability ratings.
A59: 2 — Repeatable | B59: Team is aware of calibrated probability language and Admiralty/NATO-style source rating but applies them inconsistently across products. | C59: <50% of judgments carry explicit confidence language or source rating.
A60: 3 — Defined | B60: All key judgments use calibrated probability language (e.g., the 8-level ODNI scale from "almost certain" down to "remote"). Sources are rated for reliability (A-F) and information credibility (1-6). | C60: >=90% of key judgments have calibrated language; >=90% of sources rated.
A61: 4 — Managed | B61: Template enforces calibrated language and source rating. Team references the ICD 203 nine standards in peer review. Deviations are flagged. | C61: Peer review checklist references ICD 203; deviations tracked.
A62: 5 — Optimized | B62: Forecast calibration is measured: statements labeled "likely (70-84%)" come true roughly 70-84% of the time when aggregated. Miscalibration drives retraining. | C62: Brier score or equivalent tracked for forecasts; retraining cadence defined.
A64: Collection Management Framework (CMF)
A65: Level | B65: Description | C65: Quantitative Measure
A66: 1 — Initial | B66: No Collection Management Framework exists. No mapping between what is collected and what PIRs or questions it is meant to answer. | C66: No CMF.
A67: 2 — Repeatable | B67: An informal CMF draft exists (often in a spreadsheet) listing feeds against topics but without PIR traceability. | C67: Draft CMF; <30% of sources mapped to PIRs.
A68: 3 — Defined | B68: A CMF is documented that maps each source to the PIRs and SIRs it is intended to support. Coverage gaps are visible. | C68: >=80% of sources mapped to at least one PIR; gap list maintained.
A69: 4 — Managed | B69: CMF is reviewed quarterly; gaps drive source addition/retirement decisions. Sources are CRAAP-evaluated and tagged for collection technique (passive vs. active). | C69: Quarterly CMF review; CRAAP ratings on >=80% of sources.
A70: 5 — Optimized | B70: CMF drives an explicit collection plan per PIR. Source cost, coverage, and ROI are tracked; decisions are defensible to leadership and auditors. | C70: Collection plan per PIR; ROI metric per source.
A72: Tier 2: Operational
A73: A Threat Intelligence Platform (or equivalent) is in place; IOC flow to SIEM and EDR is automated; Detection Engineering handoff is scheduled; CTI partners with the dedicated Threat Hunting team on a cadence; and Incident Response is enriched with CTI context on every incident. This is where CTI becomes visible in day-to-day SOC operations.
A74: Threat Intelligence Platform and IOC Pipeline
A75: Level | B75: Description | C75: Quantitative Measure
A76: 1 — Initial | B76: No TIP. IOCs live in spreadsheets, emails, or SIEM watchlists updated by hand. No systematic ingestion, enrichment, or expiration. | C76: No TIP; manual IOC management.
A77: 2 — Repeatable | B77: A TIP (OpenCTI, MISP, ThreatConnect, Anomali, Recorded Future, etc.) is deployed but underutilized. Some feeds ingested; manual export to SIEM. | C77: TIP in place; <50% of feeds ingested; manual SIEM push.
A78: 3 — Defined | B78: TIP ingests multiple feeds via STIX/TAXII or API. Indicators are enriched on ingestion, tagged with TLP and source, and pushed to the SIEM via automation. IOC expiration is automated. | C78: >=5 feeds automated; SIEM push via API; expiration policy configured.
A79: 4 — Managed | B79: Closed-loop feedback: SOC triage verdicts (true/false positive) flow back to TIP and adjust source fidelity scoring. Low-fidelity indicators are deprioritized; high-fidelity can trigger SOAR-based blocking. | C79: SOC feedback pipeline in production; source scoring adjusts based on verdicts.
A80: 5 — Optimized | B80: TIP is the single source of truth for indicators across SIEM, EDR, SOAR, and firewalls. TIP analytics (pivoting, relationship graphs) are part of the analyst workflow. Pipeline health is monitored. | C80: TIP is single source of truth; analyst pivoting in TIP standard; pipeline SLOs tracked.
A82: Detection Engineering Handoff
A83: Level | B83: Description | C83: Quantitative Measure
A84: 1 — Initial | B84: CTI and Detection Engineering interact ad-hoc. Detection requests are verbal or email; no backlog, no tracking, no provenance once rules ship. | C84: No shared backlog; no rule-level CTI provenance.
A85: 2 — Repeatable | B85: CTI submits occasional detection requests but without a template. DE sometimes responds; no formal cadence. | C85: <1 formal request per month; no cadence.
A86: 3 — Defined | B86: Monthly (or more frequent) CTI-to-DE cadence. Requests use a standard template (threat, TTP, ATT&CK ID, suggested logic). CTI-originated requests are tracked through the DE pipeline. | C86: >=1 cadence per month; template in use; backlog visible to both teams.
A87: 4 — Managed | B87: CTI-driven detections are tagged in the Detection-as-Code repository with PIR/CTI source references. Rule hit rate and false-positive rate are measured against CTI-driven rules. | C87: CTI tag applied in DaC repo; hit rate / FP rate metrics produced.
A88: 5 — Optimized | B88: Lead time from CTI request to deployed detection is measured. ATT&CK coverage driven by CTI inputs is mapped from the detection repo. CTI influences DE roadmap at planning meetings. | C88: Lead-time metric reported; ATT&CK coverage map auto-generated.
A90: Collaboration with the Threat Hunting Team
A91: Level | B91: Description | C91: Quantitative Measure
A92: 1 — Initial | B92: No working relationship with the dedicated Threat Hunting team. CTI does not feed hunt ideas; hunt findings do not flow back to CTI. | C92: No cadence or structured handoff; hunt team operates without CTI input.
A93: 2 — Repeatable | B93: Informal, ad-hoc interaction when an analyst from either side reaches out. CTI occasionally emails an IOC or actor name to the hunt team; findings rarely come back. | C93: <1 structured intel-to-hunt handoff per month; no return feedback path.
A94: 3 — Defined | B94: A recurring CTI-to-Hunt cadence exists (at least monthly). CTI submits hunt hypothesis abstracts to the hunt backlog, scoped against PIRs and MITRE ATT&CK. Hunts target the upper tiers of the Pyramid of Pain (TTPs and tools) using CTI-provided adversary packages. | C94: >=1 CTI-to-Hunt cadence per month; >=3 CTI-submitted hunt abstracts per quarter.
A95: 4 — Managed | B95: Hunt findings flow back to CTI on a defined path and update the threat profile, PIRs, and the Collection Management Framework. CTI provides enriched intel views (actor, campaign, Diamond Model, ATT&CK Navigator layers) to scope active hunts. TaHiTI-style three-phase flow is followed end-to-end. | C95: >=80% of hunts scoped with a CTI package; documented return-feedback path in use.
A96: 5 — Optimized | B96: CTI-Hunt partnership is measured: % of hunts sourced by CTI, % of hunts producing a traceable downstream CTI or detection artifact, and lessons-learned retrospectives on cadence. PIRs and the CMF are routinely updated based on hunt findings. | C96: CTI-Hunt KPIs reported quarterly; measurable improvement in hunt yield year-over-year.
A98: Incident Response Enrichment
A99: Level | B99: Description | C99: Quantitative Measure
A100: 1 — Initial | B100: CTI is not systematically engaged during incidents. IR analysts search for context themselves; CTI may contribute if asked. | C100: CTI involvement in <30% of major incidents.
A101: 2 — Repeatable | B101: CTI provides enrichment when asked. Post-incident, CTI sometimes adds context to the report. | C101: Ad-hoc enrichment; not tracked; no SLA.
A102: 3 — Defined | B102: Every incident ticket above a defined severity is enriched with CTI context (known actor / TTPs / campaign / prior observations). A named CTI liaison supports IR on-call. | C102: >=90% of high-sev incidents enriched; on-call liaison named.
A103: 4 — Managed | B103: Enrichment is automated via TIP/SOAR on ticket creation. Incident TTPs are mapped to ATT&CK and the Diamond Model. Post-incident, CTI contributes to lessons-learned. | C103: Automated enrichment in production; ATT&CK mapping on >=80% of IR cases.
A104: 5 — Optimized | B104: CTI-driven post-incident assessments produce updates to PIRs, detection backlog, and threat profile. Incident contribution metrics (MTTD/MTTR improvement) are tracked where measurable. | C104: Post-incident CTI output traceable to downstream changes; MTTR attribution measured.
A106: Tier 3: Advanced
A107: CTI produces specialized intelligence for telco-context stakeholders (Vulnerability Management, Fraud, Third-Party Risk) and delivers a recurring Cyber Threat Landscape product at strategic/operational/tactical tiers. Outcome metrics are defined and reported.
A108: Vulnerability and Exploit Intelligence
A109: Level | B109: Description | C109: Quantitative Measure
A110: 1 — Initial | B110: No vulnerability intelligence contribution to Vulnerability Management. VM prioritizes on CVSS alone. | C110: No CTI input to VM prioritization.
A111: 2 — Repeatable | B111: Ad-hoc alerts on viral CVEs (the "log4j moment" pattern). No cadence. No telco-stack specificity. | C111: Reactive CVE alerts; no cadence; no telco-stack tagging.
A112: 3 — Defined | B112: Bi-weekly or monthly vulnerability intelligence brief to VM covering newly-disclosed CVEs relevant to the telco technology stack (RAN, core, transport, billing/OSS/BSS, hyperscaler, CPE). | C112: Recurring VM brief; telco-tech tagging applied.
A113: 4 — Managed | B113: EPSS, exploit-in-the-wild observation, and underground chatter are integrated. CTI-contributed score modifiers feed VM prioritization. Telco-specific protocol vulns (SS7, Diameter, GTP, 5G) are tracked. | C113: EPSS + exploit-observation inputs in VM; telco protocol coverage documented.
...

Sheet Glossary
A1: TIBMM Glossary
A2: Definitions of terms referenced in the rubric and assessment. Use this tab if any term in a question is unfamiliar.
B4: Term | C4: Category | D4: Definition
B5: Direction
B6: PIR | C6: Direction | D6: Priority Intelligence Requirement. A documented question that a stakeholder needs CTI to answer on a recurring basis. PIRs drive what CTI collects, analyzes, and produces. A mature CTI function has 6-12 active PIRs each tied to a named stakeholder and a business question.
B7: RFI | C7: Direction | D7: Request for Information. A stakeholder-initiated ad-hoc question outside the standing PIR set (e.g., "what do we know about actor X?").
B8: SIR | C8: Direction | D8: Specific Intelligence Requirement. A narrower decomposition of a PIR into one or more concrete, collectable questions. Example: PIR "What ransomware groups target Canadian telecom?" decomposes into SIRs like "Which ransomware groups have publicly claimed Canadian telecom victims in the last 12 months?"
B9: Product Structure
B10: BLUF | C10: Product Structure | D10: Bottom Line Up Front. The intelligence-writing convention that places the key analytic judgment and recommendation in the first paragraph, before any background. Codified in the SANS Intelligence Analyst's Playbook. Distinct from an executive summary: BLUF is the judgment itself, not a preview.
B11: Tradecraft
B12: ACH | C12: Tradecraft | D12: Analysis of Competing Hypotheses. Richards Heuer's 8-step SAT that evaluates multiple explanations against the same evidence simultaneously, looking for the hypothesis least inconsistent with the evidence (rather than the one most consistent). Designed to combat confirmation bias.
B13: Admiralty Code / NATO Source Rating | C13: Tradecraft | D13: A two-dimensional source and information evaluation system. Source reliability is rated A (completely reliable) through F (cannot be judged); information credibility is rated 1 (confirmed) through 6 (cannot be judged). Source and information are rated independently; a piece of intelligence might be "B2" (usually reliable source, probably true).
B14: Calibrated Probability Language | C14: Tradecraft | D14: A fixed probability scale used to express confidence. The ODNI 8-level scale: almost certain (93-99%), very likely (85-92%), likely (70-84%), probable (55-69%), roughly even (45-54%), unlikely (15-44%), very unlikely (3-14%), remote (1-2%). The point is to prevent "likely" meaning 55% to one reader and 85% to another. Never use 100% or 0%.
B15: CRAAP | C15: Tradecraft | D15: Currency, Relevance, Authority, Accuracy, Purpose. A lightweight framework for evaluating a source of intelligence information. Currency: how recent? Relevance: does it address the question? Authority: who produced it? Accuracy: is it verifiable? Purpose: why was it published?
B16: ICD 203 | C16: Tradecraft | D16: Intelligence Community Directive 203 (ODNI, Jan 2015, amended 2022). Defines nine analytic tradecraft standards governing US IC finished intelligence: (1) describe source quality, (2) express uncertainty with calibrated language, (3) distinguish information from assumption, (4) incorporate analysis of alternatives, (5) demonstrate customer relevance, (6) use clear argumentation, (7) explain change or consistency, (8) make accurate judgments, (9) use effective visuals. TIBMM adopts these as the tradecraft floor for product-producing activity.
B17: SAT | C17: Tradecraft | D17: Structured Analytic Technique. Formal methods for combating cognitive bias in analysis. Common SATs: Analysis of Competing Hypotheses (ACH), Key Assumptions Check, Pre-Mortem, Devil's Advocacy, Red Team Analysis. TIBMM expects at least one SAT applied to every major product at Tier 4.
B18: Collection
B19: CMF | C19: Collection | D19: Collection Management Framework. The document that maps each intelligence source (OSINT feed, commercial feed, ISAC, vendor portal, internal telemetry) to the PIRs and SIRs it is intended to support. The CMF makes collection gaps visible and justifies source spend. At a minimum, a CMF is a spreadsheet with columns: Source, Type, Owner, Cost, PIRs Supported, Coverage Notes.
B20: Sharing
B21: CCTX | C21: Sharing | D21: Canadian Cyber Threat Exchange. National not-for-profit cross-sector threat intelligence sharing community. Most Canadian critical-infrastructure organizations, including telcos, participate. Membership is expected at TIBMM Tier-3+.
B22: ISAC | C22: Sharing | D22: Information Sharing and Analysis Center. Industry-specific threat-sharing communities (e.g., FS-ISAC for finance, H-ISAC for health). The telco sector participates in the Communications ISAC (Comm-ISAC) in the US and similar fora elsewhere; CCTX is the Canadian cross-sector equivalent.
B23: TLP | C23: Sharing | D23: Traffic Light Protocol. The standard marking convention for sensitivity of shared intelligence: RED (named recipients only), AMBER (limited distribution within organization), AMBER+STRICT (org only, not for vendors/partners), GREEN (community/sector), CLEAR (public, formerly WHITE).
B24: Tooling
B25: SOAR | C25: Tooling | D25: Security Orchestration, Automation, and Response. Playbook-driven automation that ties alerts, enrichment lookups, and response actions together. CTI integrates with SOAR so high-confidence indicators can trigger automated blocking and SOC alerts can auto-enrich with TIP context.
B26: STIX / TAXII | C26: Tooling | D26: STIX (Structured Threat Information Expression) is the standard data format for sharing CTI. TAXII (Trusted Automated Exchange of Indicator Information) is the transport protocol for pulling/pushing STIX. Most TIPs, SIEMs, and ISAC feeds support STIX/TAXII natively.
B27: TIP | C27: Tooling | D27: Threat Intelligence Platform. The category of tool that aggregates, enriches, stores, scores, and distributes threat intelligence across feeds and internal systems. Examples: OpenCTI (open-source), MISP (open-source), ThreatConnect, Anomali, Recorded Future. A TIP acts as the single source of truth for indicators across SIEM/EDR/SOAR.
B28: Vulnerability
B29: EPSS | C29: Vulnerability | D29: Exploit Prediction Scoring System. A probabilistic scoring system from FIRST (0-1 scale) indicating the likelihood a CVE will be exploited in the wild in the next 30 days. Complements CVSS (which measures severity, not exploitation probability). CTI-feeding EPSS-augmented prioritization to Vulnerability Management is a common T3 practice.
B30: Tactical
B31: IOC | C31: Tactical | D31: Indicator of Compromise. Atomic artifact signaling potentially malicious activity: IP address, domain, URL, file hash, email address, registry key. At the bottom of Bianco's Pyramid of Pain; easy for adversaries to change.
B32: Tactical / Behavioral
B33: TTP | C33: Tactical / Behavioral | D33: Tactic, Technique, Procedure. The behavioral description of adversary actions, higher on the Pyramid of Pain than IOCs because TTPs are harder for adversaries to change. MITRE ATT&CK catalogs TTPs at the technique and sub-technique level.
B34: Framework
B35: ATT&CK | C35: Framework | D35: MITRE's knowledge base of adversary tactics, techniques, and sub-techniques based on real-world observations. Currently v18 with ~216 techniques and ~475 sub-techniques. Organized by 14 tactics (Initial Access through Impact). ATT&CK IDs are the standard shorthand in CTI, detection, and hunt products.
B36: Cyber Kill Chain | C36: Framework | D36: Lockheed Martin's 7-phase model of an intrusion: Reconnaissance, Weaponization, Delivery, Exploitation, Installation, Command & Control, Actions on Objectives. Largely superseded by ATT&CK for granular analysis but still useful as a high-level campaign narrative structure.
B37: Diamond Model | C37: Framework | D37: Intrusion analysis framework (Caltagirone, Pendergast, Betz 2013) with four vertices: Adversary, Capability, Infrastructure, Victim. Used to describe the relational structure of an intrusion and to pivot investigations. Complementary to ATT&CK, which describes what adversaries do; Diamond describes the relationships between actors, tools, victims, and infrastructure.
B38: Pyramid of Pain | C38: Framework | D38: David Bianco's concept ranking indicator types by how much pain they cause adversaries to change. Bottom (easy to change): hash values, IP addresses, domain names. Middle: network artifacts, host artifacts. Top (painful to change): tools, TTPs. Hunts and detections should aim for the upper tiers.
B39: Hunt Methodology
B40: MaGMa | C40: Hunt Methodology | D40: Use Case Framework / tool that accompanies TaHiTI, used to structure hunt outcomes and measure hunt team performance over time.
B41: TaHiTI | C41: Hunt Methodology | D41: Targeted Hunting integrating Threat Intelligence. A threat-hunting methodology from FI-ISAC / Dutch Payments Association. Three phases: Initialize (generate hunt hypothesis abstract from CTI, IR, red team, or MaGMa gap), Hunt (refine hypothesis with CTI-enriched view, execute), Finalize (document findings; hand off to DE, IR, or back to CTI). The framework explicitly places CTI as the upstream producer of hunt hypotheses.
B42: Metrics
B43: Brier Score | C43: Metrics | D43: A scoring rule for probabilistic forecasts. Lower is better (0 = perfect, 1 = worst). Used to measure forecast calibration across many predictions: does a CTI judgment tagged "likely (70-84%)" come true roughly 70-84% of the time when aggregated? Feeds ICD 203 standard 8 (accurate judgments).
B44: NPS | C44: Metrics | D44: Net Promoter Score. "How likely are you to recommend working with CTI on intelligence questions in your domain?" on a 0-10 scale. Used in TIBMM to capture stakeholder satisfaction per domain on an annual cycle.
B45: Reporting
B46: ENISA CTL | C46: Reporting | D46: European Union Agency for Cybersecurity's Cyber Threat Landscape methodology. Standard structure for recurring threat landscape reporting: identify prime threats, map actors and motivations, describe techniques, summarize events, project trends. TIBMM references this as the methodology to follow for the quarterly CTL product.
B47: Canadian Regulatory
B48: Bill C-26 / CCSPA | C48: Canadian Regulatory | D48: Critical Cyber Systems Protection Act (passed as part of Bill C-26, 2024). Imposes cybersecurity program, incident-reporting, and direction-compliance obligations on designated operators including Canadian telecommunications providers. CTI is likely to be a named input to the CCSPA-required cybersecurity program.
B49: CASL | C49: Canadian Regulatory | D49: Canada's Anti-Spam Legislation. Restricts commercial electronic messages; relevant to CTI when collecting phishing/smishing samples and when sharing threat samples externally.
B50: CCCS / CSE | C50: Canadian Regulatory | D50: Canadian Centre for Cyber Security, part of the Communications Security Establishment (CSE). Federal body issuing cyber advisories, threat bulletins, and sector guidance. Telco CTI should ingest CCCS advisories as a named source and maintain a CCCS liaison path.
B51: CRTC | C51: Canadian Regulatory | D51: Canadian Radio-television and Telecommunications Commission. Federal telecom regulator. Issues cybersecurity expectations for carriers; requires reporting of certain network-security incidents. Strategic CTI products to leadership should synthesize CRTC expectations as part of regulatory context.
B52: PIPEDA | C52: Canadian Regulatory | D52: Personal Information Protection and Electronic Documents Act. Canada's federal privacy law governing how private-sector organizations collect, use, and disclose personal information. Relevant to CTI when collecting or storing indicators that contain personal data (emails, phone numbers, names), particularly from credential leaks or underground-forum observation.
B53: Telco Fraud
B54: Number Porting Abuse | C54: Telco Fraud | D54: Closely related to SIM swap: abuse of Local Number Portability processes across carriers. Canadian telcos face this threat directly given CRTC porting rules; CTI tracks cross-carrier porting-abuse campaigns.
B55: SIM Swap | C55: Telco Fraud | D55: Fraud technique where an attacker socially engineers or insider-assists a carrier to port a victim's phone number to an attacker-controlled SIM, intercepting SMS-based 2FA. CTI on SIM-swap actor TTPs (recruitment of insiders, tooling, target sectors) supports Fraud and IAM teams.
B56: Smishing | C56: Telco Fraud | D56: SMS phishing. A fraud category particularly acute for telcos because the carrier's own infrastructure is the delivery channel. Smishing kits are collected, analyzed, and shared; indicators (sender numbers, lure URLs, kit infrastructure) feed SIEM/EDR and anti-fraud detection.
B57: Telco Stack
B58: 5G / SBA | C58: Telco Stack | D58: 5G's Service-Based Architecture introduces HTTP/2-based NF-to-NF signaling (Network Function service-based interfaces). New attack surface (NRF impersonation, AMF/SMF abuse). CTI on 5G-specific research and disclosed vulnerabilities feeds the T3 VM practice.
B59: CPE | C59: Telco Stack | D59: Customer Premises Equipment. Consumer/business modems, routers, ONTs. CPE compromise is a telco-visible fraud and abuse vector (botnet recruitment, DDoS amplification). CPE-vendor supply-chain intelligence is a TPRM topic.
B60: OSS / BSS | C60: Telco Stack | D60: Operational Support Systems / Business Support Systems. The carrier's back-end stack: network management, provisioning, billing, CRM, mediation. Vulnerability intelligence on OSS/BSS platforms (Amdocs, Netcracker, Oracle BRM, etc.) is a scored practice at T3.
B61: RAN | C61: Telco Stack | D61: Radio Access Network. The wireless edge (cell sites, base stations, NodeB/eNodeB/gNodeB). RAN vendors include Ericsson, Nokia, Samsung, Huawei. Vulnerability and supply-chain intelligence on RAN vendors is in scope for TIBMM T3 Vuln and TPRM practices.
B62: SS7 / Diameter / GTP | C62: Telco Stack | D62: Telecommunications signaling protocols. SS7 (legacy 2G/3G signaling), Diameter (4G/LTE signaling), GTP (GPRS/4G/5G user-plane and signaling). Each has well-documented abuse cases (location tracking, SMS interception, billing fraud, DoS). Vulnerability intelligence on these protocols, and changes in their threat landscape, are in scope for telco CTI.

Sheet Report Data
A1: SUMMARY
A2: Organization | B2: =Assessment!D4
A3: Assessor | B3: =Assessment!D5
A4: Date | B4: =Assessment!D7
A5: Assessment Type | B5: =Assessment!D8
A6: Overall Score | B6: =IF(COUNT(D18,D19,D20,D21,D22,D23,D24,D25,D26,D27,D28,D29,D30,D31,D32,D33,D34,D35,D36,D37,D38,D39,D40,D41,D42,D43)=0,"",ROUND(AVERAGE(D18,D19,D20,D21,D22,D23,D24,D25,D26,D27,D28,D29,D30,D31,D32,D33,D34,D35,D36,D37,D38,D39,D40,D41,D42,D43),2))
A7: Achieved Tier | B7: =IF(AND(AND(ISNUMBER(D18),D18>=3,ISNUMBER(D19),D19>=3,ISNUMBER(D20),D20>=3,ISNUMBER(D21),D21>=3),AND(ISNUMBER(D22),D22>=3,ISNUMBER(D23),D23>=3,ISNUMBER(D24),D24>=3,ISNUMBER(D25),D25>=3),AND(ISNUMBER(D26),D26>=3,ISNUMBER(D27),D27>=3,ISNUMBER(D28),D28>=3,ISNUMBER(D29),D29>=3),AND(ISNUMBER(D30),D30>=3,ISNUMBER(D31),D31>=3,ISNUMBER(D32),D32>=3,ISNUMBER(D33),D33>=3),AND(ISNUMBER(D34),D34>=3,ISNUMBER(D35),D35>=3,ISNUMBER(D36),D36>=3,ISNUMBER(D37),D37>=3)),"Tier 4: Leading",IF(AND(AND(ISNUMBER(D18),D18>=3,ISNUMBER(D19),D19>=3,ISNUMBER(D20),D20>=3,ISNUMBER(D21),D21>=3),AND(ISNUMBER(D22),D22>=3,ISNUMBER(D23),D23>=3,ISNUMBER(D24),D24>=3,ISNUMBER(D25),D25>=3),AND(ISNUMBER(D26),D26>=3,ISNUMBER(D27),D27>=3,ISNUMBER(D28),D28>=3,ISNUMBER(D29),D29>=3),AND(ISNUMBER(D30),D30>=3,ISNUMBER(D31),D31>=3,ISNUMBER(D32),D32>=3,ISNUMBER(D33),D33>=3)),"Tier 3: Advanced",IF(AND(AND(ISNUMBER(D18),D18>=3,ISNUMBER(D19),D19>=3,ISNUMBER(D20),D20>=3,ISNUMBER(D21),D21>=3),AND(ISNUMBER(D22),D22>=3,ISNUMBER(D23),D23>=3,ISNUMBER(D24),D24>=3,ISNUMBER(D25),D25>=3),AND(ISNUMBER(D26),D26>=3,ISNUMBER(D27),D27>=3,ISNUMBER(D28),D28>=3,ISNUMBER(D29),D29>=3)),"Tier 2: Operational",IF(AND(AND(ISNUMBER(D18),D18>=3,ISNUMBER(D19),D19>=3,ISNUMBER(D20),D20>=3,ISNUMBER(D21),D21>=3),AND(ISNUMBER(D22),D22>=3,ISNUMBER(D23),D23>=3,ISNUMBER(D24),D24>=3,ISNUMBER(D25),D25>=3)),"Tier 1: Basic",IF(AND(AND(ISNUMBER(D18),D18>=3,ISNUMBER(D19),D19>=3,ISNUMBER(D20),D20>=3,ISNUMBER(D21),D21>=3)),"Tier 0: Foundation","Below Foundation")))))
A8: Completion | B8: =COUNTA(Assessment!E15,Assessment!E16,Assessment!E17,Assessment!E18,Assessment!E19,Assessment!E20,Assessment!E23,Assessment!E24,Assessment!E25,Assessment!E26,Assessment!E27,Assessment!E28,Assessment!E31,Assessment!E32,Assessment!E33,Assessment!E34,Assessment!E35,Assessment!E36,Assessment!E39,Assessment!E40,Assessment!E41,Assessment!E42,Assessment!E43,Assessment!E46,Assessment!E47,Assessment!E48,Assessment!E49,Assessment!E50,Assessment!E57,Assessment!E58,Assessment!E59,Assessment!E60,Assessment!E63,Assessment!E64,Assessment!E65)&" / 35"
A10: Tier | B10: Tier Name | C10: Score | D10: Level | E10: Status | F10: Progression
A11: T0 | B11: Foundation | C11: =IF(COUNT(Assessment!F15,Assessment!F16,Assessment!F17,Assessment!F18,Assessment!F19,Assessment!F20)=0,"",AVERAGE(Assessment!F15,Assessment!F16,Assessment!F17,Assessment!F18,Assessment!F19,Assessment!F20)) | D11: =IF(C11="","",IF(C11>=4.5,"Optimized",IF(C11>=3.5,"Managed",IF(C11>=2.5,"Defined",IF(C11>=1.5,"Repeatable","Initial"))))) | E11: =IF(C11="","",IF(C11>=3,"✓ Pass","✗ Below Target")) | F11: =IF(C11="","Not Started",IF(AND(AND(ISNUMBER(D18),D18>=3,ISNUMBER(D19),D19>=3,ISNUMBER(D20),D20>=3,ISNUMBER(D21),D21>=3)),"Complete",IF(TRUE,"Current","In Progress")))
A12: T1 | B12: Basic | C12: =IF(COUNT(Assessment!F23,Assessment!F24,Assessment!F25,Assessment!F26,Assessment!F27,Assessment!F28)=0,"",AVERAGE(Assessment!F23,Assessment!F24,Assessment!F25,Assessment!F26,Assessment!F27,Assessment!F28)) | D12: =IF(C12="","",IF(C12>=4.5,"Optimized",IF(C12>=3.5,"Managed",IF(C12>=2.5,"Defined",IF(C12>=1.5,"Repeatable","Initial"))))) | E12: =IF(C12="","",IF(C12>=3,"✓ Pass","✗ Below Target")) | F12: =IF(C12="","Not Started",IF(AND(AND(ISNUMBER(D18),D18>=3,ISNUMBER(D19),D19>=3,ISNUMBER(D20),D20>=3,ISNUMBER(D21),D21>=3),AND(ISNUMBER(D22),D22>=3,ISNUMBER(D23),D23>=3,ISNUMBER(D24),D24>=3,ISNUMBER(D25),D25>=3)),"Complete",IF(AND(AND(ISNUMBER(D18),D18>=3,ISNUMBER(D19),D19>=3,ISNUMBER(D20),D20>=3,ISNUMBER(D21),D21>=3)),"Current","In Progress")))
A13: T2 | B13: Operational | C13: =IF(COUNT(Assessment!F31,Assessment!F32,Assessment!F33,Assessment!F34,Assessment!F35,Assessment!F36)=0,"",AVERAGE(Assessment!F31,Assessment!F32,Assessment!F33,Assessment!F34,Assessment!F35,Assessment!F36)) | D13: =IF(C13="","",IF(C13>=4.5,"Optimized",IF(C13>=3.5,"Managed",IF(C13>=2.5,"Defined",IF(C13>=1.5,"Repeatable","Initial"))))) | E13: =IF(C13="","",IF(C13>=3,"✓ Pass","✗ Below Target")) | F13: =IF(C13="","Not Started",IF(AND(AND(ISNUMBER(D18),D18>=3,ISNUMBER(D19),D19>=3,ISNUMBER(D20),D20>=3,ISNUMBER(D21),D21>=3),AND(ISNUMBER(D22),D22>=3,ISNUMBER(D23),D23>=3,ISNUMBER(D24),D24>=3,ISNUMBER(D25),D25>=3),AND(ISNUMBER(D26),D26>=3,ISNUMBER(D27),D27>=3,ISNUMBER(D28),D28>=3,ISNUMBER(D29),D29>=3)),"Complete",IF(AND(AND(ISNUMBER(D18),D18>=3,ISNUMBER(D19),D19>=3,ISNUMBER(D20),D20>=3,ISNUMBER(D21),D21>=3),AND(ISNUMBER(D22),D22>=3,ISNUMBER(D23),D23>=3,ISNUMBER(D24),D24>=3,ISNUMBER(D25),D25>=3)),"Current","In Progress")))
A14: T3 | B14: Advanced | C14: =IF(COUNT(Assessment!F39,Assessment!F40,Assessment!F41,Assessment!F42,Assessment!F43)=0,"",AVERAGE(Assessment!F39,Assessment!F40,Assessment!F41,Assessment!F42,Assessment!F43)) | D14: =IF(C14="","",IF(C14>=4.5,"Optimized",IF(C14>=3.5,"Managed",IF(C14>=2.5,"Defined",IF(C14>=1.5,"Repeatable","Initial"))))) | E14: =IF(C14="","",IF(C14>=3,"✓ Pass","✗ Below Target")) | F14: =IF(C14="","Not Started",IF(AND(AND(ISNUMBER(D18),D18>=3,ISNUMBER(D19),D19>=3,ISNUMBER(D20),D20>=3,ISNUMBER(D21),D21>=3),AND(ISNUMBER(D22),D22>=3,ISNUMBER(D23),D23>=3,ISNUMBER(D24),D24>=3,ISNUMBER(D25),D25>=3),AND(ISNUMBER(D26),D26>=3,ISNUMBER(D27),D27>=3,ISNUMBER(D28),D28>=3,ISNUMBER(D29),D29>=3),AND(ISNUMBER(D30),D30>=3,ISNUMBER(D31),D31>=3,ISNUMBER(D32),D32>=3,ISNUMBER(D33),D33>=3)),"Complete",IF(AND(AND(ISNUMBER(D18),D18>=3,ISNUMBER(D19),D19>=3,ISNUMBER(D20),D20>=3,ISNUMBER(D21),D21>=3),AND(ISNUMBER(D22),D22>=3,ISNUMBER(D23),D23>=3,ISNUMBER(D24),D24>=3,ISNUMBER(D25),D25>=3),AND(ISNUMBER(D26),D26>=3,ISNUMBER(D27),D27>=3,ISNUMBER(D28),D28>=3,ISNUMBER(D29),D29>=3)),"Current","In Progress")))
A15: T4 | B15: Leading | C15: =IF(COUNT(Assessment!F46,Assessment!F47,Assessment!F48,Assessment!F49,Assessment!F50)=0,"",AVERAGE(Assessment!F46,Assessment!F47,Assessment!F48,Assessment!F49,Assessment!F50)) | D15: =IF(C15="","",IF(C15>=4.5,"Optimized",IF(C15>=3.5,"Managed",IF(C15>=2.5,"Defined",IF(C15>=1.5,"Repeatable","Initial"))))) | E15: =IF(C15="","",IF(C15>=3,"✓ Pass","✗ Below Target")) | F15: =IF(C15="","Not Started",IF(AND(AND(ISNUMBER(D18),D18>=3,ISNUMBER(D19),D19>=3,ISNUMBER(D20),D20>=3,ISNUMBER(D21),D21>=3),AND(ISNUMBER(D22),D22>=3,ISNUMBER(D23),D23>=3,ISNUMBER(D24),D24>=3,ISNUMBER(D25),D25>=3),AND(ISNUMBER(D26),D26>=3,ISNUMBER(D27),D27>=3,ISNUMBER(D28),D28>=3,ISNUMBER(D29),D29>=3),AND(ISNUMBER(D30),D30>=3,ISNUMBER(D31),D31>=3,ISNUMBER(D32),D32>=3,ISNUMBER(D33),D33>=3),AND(ISNUMBER(D34),D34>=3,ISNUMBER(D35),D35>=3,ISNUMBER(D36),D36>=3,ISNUMBER(D37),D37>=3)),"Complete",IF(AND(AND(ISNUMBER(D18),D18>=3,ISNUMBER(D19),D19>=3,ISNUMBER(D20),D20>=3,ISNUMBER(D21),D21>=3),AND(ISNUMBER(D22),D22>=3,ISNUMBER(D23),D23>=3,ISNUMBER(D24),D24>=3,ISNUMBER(D25),D25>=3),AND(ISNUMBER(D26),D26>=3,ISNUMBER(D27),D27>=3,ISNUMBER(D28),D28>=3,ISNUMBER(D29),D29>=3),AND(ISNUMBER(D30),D30>=3,ISNUMBER(D31),D31>=3,ISNUMBER(D32),D32>=3,ISNUMBER(D33),D33>=3)),"Current","In Progress")))
A17: Section | B17: Category | C17: Criterion | D17: Score | E17: Level | F17: Status
A18: TIBMM Core | B18: Foundation | C18: Mission, Charter, and Service Catalog | D18: =IF(COUNT(Assessment!F15,Assessment!F16)=0,"",AVERAGE(Assessment!F15,Assessment!F16)) | E18: =IF(D18="","",IF(D18>=4.5,"Optimized",IF(D18>=3.5,"Managed",IF(D18>=2.5,"Defined",IF(D18>=1.5,"Repeatable","Initial"))))) | F18: =IF(D18="","",IF(D18>=3,"✓ Pass","✗ Below Target"))
A19: TIBMM Core | B19: Foundation | C19: Indicator of Compromise Handling | D19: =IF(COUNT(Assessment!F17,Assessment!F18)=0,"",AVERAGE(Assessment!F17,Assessment!F18)) | E19: =IF(D19="","",IF(D19>=4.5,"Optimized",IF(D19>=3.5,"Managed",IF(D19>=2.5,"Defined",IF(D19>=1.5,"Repeatable","Initial"))))) | F19: =IF(D19="","",IF(D19>=3,"✓ Pass","✗ Below Target"))
A20: TIBMM Core | B20: Foundation | C20: Intelligence Source Inventory | D20: =IF(COUNT(Assessment!F19)=0,"",AVERAGE(Assessment!F19)) | E20: =IF(D20="","",IF(D20>=4.5,"Optimized",IF(D20>=3.5,"Managed",IF(D20>=2.5,"Defined",IF(D20>=1.5,"Repeatable","Initial"))))) | F20: =IF(D20="","",IF(D20>=3,"✓ Pass","✗ Below Target"))
A21: TIBMM Core | B21: Foundation | C21: Stakeholder Awareness and Access | D21: =IF(COUNT(Assessment!F20)=0,"",AVERAGE(Assessment!F20)) | E21: =IF(D21="","",IF(D21>=4.5,"Optimized",IF(D21>=3.5,"Managed",IF(D21>=2.5,"Defined",IF(D21>=1.5,"Repeatable","Initial"))))) | F21: =IF(D21="","",IF(D21>=3,"✓ Pass","✗ Below Target"))
A22: TIBMM Core | B22: Basic | C22: Priority Intelligence Requirements (PIRs) | D22: =IF(COUNT(Assessment!F23,Assessment!F24)=0,"",AVERAGE(Assessment!F23,Assessment!F24)) | E22: =IF(D22="","",IF(D22>=4.5,"Optimized",IF(D22>=3.5,"Managed",IF(D22>=2.5,"Defined",IF(D22>=1.5,"Repeatable","Initial"))))) | F22: =IF(D22="","",IF(D22>=3,"✓ Pass","✗ Below Target"))
A23: TIBMM Core | B23: Basic | C23: Product Template and BLUF Structure | D23: =IF(COUNT(Assessment!F25)=0,"",AVERAGE(Assessment!F25)) | E23: =IF(D23="","",IF(D23>=4.5,"Optimized",IF(D23>=3.5,"Managed",IF(D23>=2.5,"Defined",IF(D23>=1.5,"Repeatable","Initial"))))) | F23: =IF(D23="","",IF(D23>=3,"✓ Pass","✗ Below Target"))
A24: TIBMM Core | B24: Basic | C24: Calibrated Language and Source Reliability | D24: =IF(COUNT(Assessment!F26,Assessment!F27)=0,"",AVERAGE(Assessment!F26,Assessment!F27)) | E24: =IF(D24="","",IF(D24>=4.5,"Optimized",IF(D24>=3.5,"Managed",IF(D24>=2.5,"Defined",IF(D24>=1.5,"Repeatable","Initial"))))) | F24: =IF(D24="","",IF(D24>=3,"✓ Pass","✗ Below Target"))
A25: TIBMM Core | B25: Basic | C25: Collection Management Framework (CMF) | D25: =IF(COUNT(Assessment!F28)=0,"",AVERAGE(Assessment!F28)) | E25: =IF(D25="","",IF(D25>=4.5,"Optimized",IF(D25>=3.5,"Managed",IF(D25>=2.5,"Defined",IF(D25>=1.5,"Repeatable","Initial"))))) | F25: =IF(D25="","",IF(D25>=3,"✓ Pass","✗ Below Target"))
A26: TIBMM Core | B26: Operational | C26: Threat Intelligence Platform and IOC Pipeline | D26: =IF(COUNT(Assessment!F31,Assessment!F32)=0,"",AVERAGE(Assessment!F31,Assessment!F32)) | E26: =IF(D26="","",IF(D26>=4.5,"Optimized",IF(D26>=3.5,"Managed",IF(D26>=2.5,"Defined",IF(D26>=1.5,"Repeatable","Initial"))))) | F26: =IF(D26="","",IF(D26>=3,"✓ Pass","✗ Below Target"))
A27: TIBMM Core | B27: Operational | C27: Detection Engineering Handoff | D27: =IF(COUNT(Assessment!F33)=0,"",AVERAGE(Assessment!F33)) | E27: =IF(D27="","",IF(D27>=4.5,"Optimized",IF(D27>=3.5,"Managed",IF(D27>=2.5,"Defined",IF(D27>=1.5,"Repeatable","Initial"))))) | F27: =IF(D27="","",IF(D27>=3,"✓ Pass","✗ Below Target"))
A28: TIBMM Core | B28: Operational | C28: Collaboration with the Threat Hunting Team | D28: =IF(COUNT(Assessment!F34,Assessment!F35)=0,"",AVERAGE(Assessment!F34,Assessment!F35)) | E28: =IF(D28="","",IF(D28>=4.5,"Optimized",IF(D28>=3.5,"Managed",IF(D28>=2.5,"Defined",IF(D28>=1.5,"Repeatable","Initial"))))) | F28: =IF(D28="","",IF(D28>=3,"✓ Pass","✗ Below Target"))
A29: TIBMM Core | B29: Operational | C29: Incident Response Enrichment | D29: =IF(COUNT(Assessment!F36)=0,"",AVERAGE(Assessment!F36)) | E29: =IF(D29="","",IF(D29>=4.5,"Optimized",IF(D29>=3.5,"Managed",IF(D29>=2.5,"Defined",IF(D29>=1.5,"Repeatable","Initial"))))) | F29: =IF(D29="","",IF(D29>=3,"✓ Pass","✗ Below Target"))
A30: TIBMM Core | B30: Advanced | C30: Vulnerability and Exploit Intelligence | D30: =IF(COUNT(Assessment!F39)=0,"",AVERAGE(Assessment!F39)) | E30: =IF(D30="","",IF(D30>=4.5,"Optimized",IF(D30>=3.5,"Managed",IF(D30>=2.5,"Defined",IF(D30>=1.5,"Repeatable","Initial"))))) | F30: =IF(D30="","",IF(D30>=3,"✓ Pass","✗ Below Target"))
A31: TIBMM Core | B31: Advanced | C31: Telco Fraud Intelligence | D31: =IF(COUNT(Assessment!F40,Assessment!F41)=0,"",AVERAGE(Assessment!F40,Assessment!F41)) | E31: =IF(D31="","",IF(D31>=4.5,"Optimized",IF(D31>=3.5,"Managed",IF(D31>=2.5,"Defined",IF(D31>=1.5,"Repeatable","Initial"))))) | F31: =IF(D31="","",IF(D31>=3,"✓ Pass","✗ Below Target"))
A32: TIBMM Core | B32: Advanced | C32: Third-Party and Supply-Chain Intelligence | D32: =IF(COUNT(Assessment!F42)=0,"",AVERAGE(Assessment!F42)) | E32: =IF(D32="","",IF(D32>=4.5,"Optimized",IF(D32>=3.5,"Managed",IF(D32>=2.5,"Defined",IF(D32>=1.5,"Repeatable","Initial"))))) | F32: =IF(D32="","",IF(D32>=3,"✓ Pass","✗ Below Target"))
A33: TIBMM Core | B33: Advanced | C33: Cyber Threat Landscape Reporting | D33: =IF(COUNT(Assessment!F43)=0,"",AVERAGE(Assessment!F43)) | E33: =IF(D33="","",IF(D33>=4.5,"Optimized",IF(D33>=3.5,"Managed",IF(D33>=2.5,"Defined",IF(D33>=1.5,"Repeatable","Initial"))))) | F33: =IF(D33="","",IF(D33>=3,"✓ Pass","✗ Below Target"))
A34: TIBMM Core | B34: Leading | C34: Strategic Intelligence to Leadership | D34: =IF(COUNT(Assessment!F46)=0,"",AVERAGE(Assessment!F46)) | E34: =IF(D34="","",IF(D34>=4.5,"Optimized",IF(D34>=3.5,"Managed",IF(D34>=2.5,"Defined",IF(D34>=1.5,"Repeatable","Initial"))))) | F34: =IF(D34="","",IF(D34>=3,"✓ Pass","✗ Below Target"))
A35: TIBMM Core | B35: Leading | C35: Structured Analytic Techniques (SATs) | D35: =IF(COUNT(Assessment!F47)=0,"",AVERAGE(Assessment!F47)) | E35: =IF(D35="","",IF(D35>=4.5,"Optimized",IF(D35>=3.5,"Managed",IF(D35>=2.5,"Defined",IF(D35>=1.5,"Repeatable","Initial"))))) | F35: =IF(D35="","",IF(D35>=3,"✓ Pass","✗ Below Target"))
A36: TIBMM Core | B36: Leading | C36: Attributable Outcomes and Impact Metrics | D36: =IF(COUNT(Assessment!F48,Assessment!F49)=0,"",AVERAGE(Assessment!F48,Assessment!F49)) | E36: =IF(D36="","",IF(D36>=4.5,"Optimized",IF(D36>=3.5,"Managed",IF(D36>=2.5,"Defined",IF(D36>=1.5,"Repeatable","Initial"))))) | F36: =IF(D36="","",IF(D36>=3,"✓ Pass","✗ Below Target"))
A37: TIBMM Core | B37: Leading | C37: Forecast Calibration | D37: =IF(COUNT(Assessment!F50)=0,"",AVERAGE(Assessment!F50)) | E37: =IF(D37="","",IF(D37>=4.5,"Optimized",IF(D37>=3.5,"Managed",IF(D37>=2.5,"Defined",IF(D37>=1.5,"Repeatable","Initial"))))) | F37: =IF(D37="","",IF(D37>=3,"✓ Pass","✗ Below Target"))
A38: Enrichment | B38: Tradecraft and Analyst Capability | C38: ICD 203 Analytic Standards Adherence | D38: =IF(COUNT(Assessment!F57)=0,"",AVERAGE(Assessment!F57)) | E38: =IF(D38="","",IF(D38>=4.5,"Optimized",IF(D38>=3.5,"Managed",IF(D38>=2.5,"Defined",IF(D38>=1.5,"Repeatable","Initial"))))) | F38: =IF(D38="","",IF(D38>=3,"✓ Pass","✗ Below Target"))
A39: Enrichment | B39: Tradecraft and Analyst Capability | C39: Framework Literacy (ATT&CK, Diamond, Kill Chain) | D39: =IF(COUNT(Assessment!F58)=0,"",AVERAGE(Assessment!F58)) | E39: =IF(D39="","",IF(D39>=4.5,"Optimized",IF(D39>=3.5,"Managed",IF(D39>=2.5,"Defined",IF(D39>=1.5,"Repeatable","Initial"))))) | F39: =IF(D39="","",IF(D39>=3,"✓ Pass","✗ Below Target"))
A40: Enrichment | B40: Tradecraft and Analyst Capability | C40: Peer Review Process | D40: =IF(COUNT(Assessment!F59,Assessment!F60)=0,"",AVERAGE(Assessment!F59,Assessment!F60)) | E40: =IF(D40="","",IF(D40>=4.5,"Optimized",IF(D40>=3.5,"Managed",IF(D40>=2.5,"Defined",IF(D40>=1.5,"Repeatable","Initial"))))) | F40: =IF(D40="","",IF(D40>=3,"✓ Pass","✗ Below Target"))
A41: Enrichment | B41: Governance, Legal, Ethics, and Improvement | C41: Legal and Regulatory Review (PIPEDA, CASL, CRTC) | D41: =IF(COUNT(Assessment!F63)=0,"",AVERAGE(Assessment!F63)) | E41: =IF(D41="","",IF(D41>=4.5,"Optimized",IF(D41>=3.5,"Managed",IF(D41>=2.5,"Defined",IF(D41>=1.5,"Repeatable","Initial"))))) | F41: =IF(D41="","",IF(D41>=3,"✓ Pass","✗ Below Target"))
A42: Enrichment | B42: Governance, Legal, Ethics, and Improvement | C42: External Sharing and Trust-Group Participation | D42: =IF(COUNT(Assessment!F64)=0,"",AVERAGE(Assessment!F64)) | E42: =IF(D42="","",IF(D42>=4.5,"Optimized",IF(D42>=3.5,"Managed",IF(D42>=2.5,"Defined",IF(D42>=1.5,"Repeatable","Initial"))))) | F42: =IF(D42="","",IF(D42>=3,"✓ Pass","✗ Below Target"))
A43: Enrichment | B43: Governance, Legal, Ethics, and Improvement | C43: Continuous Improvement and Self-Assessment | D43: =IF(COUNT(Assessment!F65)=0,"",AVERAGE(Assessment!F65)) | E43: =IF(D43="","",IF(D43>=4.5,"Optimized",IF(D43>=3.5,"Managed",IF(D43>=2.5,"Defined",IF(D43>=1.5,"Repeatable","Initial"))))) | F43: =IF(D43="","",IF(D43>=3,"✓ Pass","✗ Below Target"))
